{
  "luaDataPath": "",
  "startBlackKeepTime": 1.0,
  "entityBan": "",
  "disableNpcLod": true,
  "JCDHIMNLLPE": true,
  "startFade": {
    "startFadeInDuration": 0.5,
    "startFadeOutDuration": 0.5
  },
  "endFade": {
    "startFadeOutDuration": 0.0
  },
  "actors": [
    {
      "alias": "Avatar",
      "visible": true,
      "bornPointName": "Q7227807_N10000005"
    },
    {
      "configID": 10090,
      "alias": "10090",
      "visible": true,
      "bornPointName": "Q7227807_N10090"
    },
    {
      "configID": 1035,
      "alias": "1035",
      "visible": true,
      "bornPointName": "Q7227807_N1035"
    },
    {
      "configID": 1005,
      "alias": "1005",
      "visible": true,
      "bornPointName": "Q7227807_N1005",
      "removeActorType": "REMOVE_WITH_DISAPPEAR"
    }
  ],
  "group": [
    [
      {
        "$type": "MoleMole.Config.ConfigLookAtInterAction",
        "type": "LOOK_AT",
        "aliasList": [
          "1035"
        ],
        "enableHead": true,
        "useTargetPos": true,
        "enableAbsolute": true,
        "targetPosition": {
          "x": -3010.6,
          "y": 218.324,
          "z": -4335.784
        },
        "headTurnTime": 0.5,
        "targetNpcAlias": "10090",
        "lookAtTargetType": "NONE"
      },
      {
        "$type": "MoleMole.Config.ConfigTeleportToAction",
        "type": "TELEPORT_TO",
        "aliasList": [
          "1035"
        ],
        "position": {
          "x": -3010.81,
          "y": 217.298,
          "z": -4335.004
        },
        "forward": {
          "x": -0.092,
          "z": -0.536
        },
        "openLongDisTeleport": true
      },
      {
        "$type": "MoleMole.Config.ConfigBodyLangInterAction",
        "type": "BODY_LANG",
        "aliasList": [
          "10090"
        ],
        "isContinue": true,
        "forceDoFreeStyle": true,
        "canDoRepeatFreeStyle": false
      },
      {
        "$type": "MoleMole.Config.ConfigLookAtEyeCtrlInterAction",
        "type": "LOOK_AT_EYECTRL",
        "aliasList": [
          "1035"
        ],
        "useTargetPos": false,
        "eyeRotateVecLeft": {
          "x": -2.0,
          "z": 3.0
        },
        "eyeRotateVecRight": {
          "x": -2.0,
          "z": 3.0
        },
        "turnTime": 0.1,
        "targetNpcAlias": "",
        "targetPoint": "Face"
      },
      {
        "$type": "MoleMole.Config.ConfigTeleportToAction",
        "type": "TELEPORT_TO",
        "aliasList": [
          "1005"
        ],
        "position": {
          "x": -3012.09,
          "y": 217.298,
          "z": -4335.132
        },
        "forward": {
          "x": 0.896,
          "y": -0.001,
          "z": -0.198
        },
        "openLongDisTeleport": true
      },
      {
        "$type": "MoleMole.Config.ConfigLookAtInterAction",
        "type": "LOOK_AT",
        "aliasList": [
          "1005"
        ],
        "enableHead": true,
        "headTurnTime": 0.5,
        "targetNpcAlias": "1035"
      },
      {
        "$type": "MoleMole.Config.ConfigBodyLangInterAction",
        "type": "BODY_LANG",
        "aliasList": [
          "1035"
        ],
        "isContinue": true,
        "forceDoFreeStyle": true,
        "canDoRepeatFreeStyle": false
      },
      {
        "$type": "MoleMole.Config.ConfigLookAtEyeCtrlInterAction",
        "type": "LOOK_AT_EYECTRL",
        "aliasList": [
          "10090"
        ],
        "useTargetPos": false,
        "eyeRotateVecLeft": {
          "x": 2.0,
          "z": -3.0
        },
        "eyeRotateVecRight": {
          "x": 2.0,
          "z": -3.0
        },
        "turnTime": 1.0,
        "targetNpcAlias": "",
        "targetPoint": "Face"
      },
      {
        "$type": "MoleMole.Config.ConfigHideWidgetPet",
        "type": "HIDE_WIDGET_PET",
        "isHide": true
      },
      {
        "$type": "MoleMole.Config.ConfigBlackScreenAction",
        "type": "BLACK_SCREEN",
        "blackScreenType": "KEEP_BLACK",
        "durationKeepBlack": 0.5,
        "inteePos": "",
        "textMapID": "",
        "useTextFade": true
      },
      {
        "$type": "MoleMole.Config.ConfigTimeProtectAction",
        "type": "TIME_PROTECT",
        "duration": 0.1
      },
      {
        "$type": "MoleMole.Config.ConfigTeleportToAction",
        "type": "TELEPORT_TO",
        "aliasList": [
          "Avatar"
        ],
        "position": {
          "x": -3012.005,
          "y": 217.297,
          "z": -4336.027
        },
        "forward": {
          "x": 0.857,
          "z": 0.606
        },
        "openLongDisTeleport": true
      },
      {
        "$type": "MoleMole.Config.ConfigTeleportToAction",
        "type": "TELEPORT_TO",
        "aliasList": [
          "10090"
        ],
        "position": {
          "x": -3010.625,
          "y": 217.298,
          "z": -4335.75
        },
        "forward": {
          "x": -0.427,
          "z": 0.426
        },
        "openLongDisTeleport": true
      },
      {
        "$type": "MoleMole.Config.ConfigLookAtInterAction",
        "type": "LOOK_AT",
        "aliasList": [
          "10090"
        ],
        "enableHead": true,
        "useTargetPos": true,
        "enableAbsolute": true,
        "targetPosition": {
          "x": -3010.815,
          "y": 218.76,
          "z": -4334.942
        },
        "headTurnTime": 0.5,
        "targetNpcAlias": "1035",
        "lookAtTargetType": "NONE"
      },
      {
        "$type": "MoleMole.Config.ConfigLookAtInterAction",
        "type": "LOOK_AT",
        "aliasList": [
          "Avatar"
        ],
        "enableHead": true,
        "headTurnTime": 0.5,
        "targetNpcAlias": "1035"
      }
    ],
    [
      {
        "$type": "MoleMole.Config.ConfigTimeProtectAction",
        "type": "TIME_PROTECT",
        "duration": 2.651
      },
      {
        "$type": "MoleMole.Config.ConfigCameraMoveInterAction",
        "type": "CAMERA_MOVE",
        "duration": 1.0,
        "camPosOffset": {
          "x": -3012.229,
          "y": 218.865,
          "z": -4335.633
        },
        "camForwardTargetOffset": {
          "x": -3011.273,
          "y": 218.63,
          "z": -4335.459
        },
        "camFov": 35.0,
        "lerpPattern": 6,
        "cameraBlendType": "EaseInOutCubic",
        "cutFrameTrans": {},
        "needZAxisRotate": true,
        "openCameraDither": false,
        "targetNpcAlias": "",
        "closeTreeLeafDither": true
      },
      {
        "$type": "MoleMole.Config.ConfigBlackScreenAction",
        "type": "BLACK_SCREEN",
        "blackScreenType": "FROM_BLACK",
        "durationFromBlack": 0.5,
        "inteePos": "",
        "textMapID": "",
        "useTextFade": true
      },
      {
        "$type": "MoleMole.Config.ConfigCameraMoveInterAction",
        "type": "CAMERA_MOVE",
        "delayTime": 0.1,
        "duration": 7.604,
        "camPosOffset": {
          "x": -3012.974,
          "y": 218.88,
          "z": -4335.782
        },
        "camForwardTargetOffset": {
          "x": -3012.018,
          "y": 218.645,
          "z": -4335.608
        },
        "camFov": 35.0,
        "cameraBlendType": "EaseInOutQuad",
        "cutFrameTrans": {},
        "needZAxisRotate": true,
        "openCameraDither": false,
        "targetNpcAlias": "",
        "closeTreeLeafDither": true
      },
      {
        "$type": "MoleMole.Config.ConfigBodyLangInterAction",
        "type": "BODY_LANG",
        "delayTime": 0.5,
        "aliasList": [
          "1035"
        ],
        "bodyLangParam": 4031,
        "forceDoFreeStyle": true,
        "canDoRepeatFreeStyle": false
      },
      {
        "$type": "MoleMole.Config.ConfigSteerInterAction",
        "type": "STEER_TO",
        "delayTime": 1.721,
        "duration": 1.0,
        "aliasList": [
          "1035"
        ],
        "steerType": "ABSOLUTE",
        "steerDir": {
          "x": -3011.653,
          "y": 217.298,
          "z": -4335.425
        },
        "useSteerAnim": true,
        "targetNpcAlias": ""
      },
      {
        "$type": "MoleMole.Config.ConfigLookAtInterAction",
        "type": "LOOK_AT",
        "delayTime": 1.877,
        "aliasList": [
          "1035"
        ],
        "enableHead": true,
        "useTargetPos": true,
        "enableAbsolute": true,
        "targetPosition": {
          "x": -3011.911,
          "y": 218.729,
          "z": -4336.001
        },
        "headTurnTime": 0.5,
        "targetNpcAlias": "Avatar",
        "lookAtTargetType": "NONE"
      },
      {
        "$type": "MoleMole.Config.ConfigLookAtEyeCtrlInterAction",
        "type": "LOOK_AT_EYECTRL",
        "delayTime": 2.028,
        "aliasList": [
          "1035"
        ],
        "useTargetPos": false,
        "turnTime": 0.1,
        "targetNpcAlias": "",
        "targetPoint": "Face"
      },
      {
        "$type": "MoleMole.Config.ConfigBodyLangInterAction",
        "type": "BODY_LANG",
        "delayTime": 2.372,
        "aliasList": [
          "1035"
        ],
        "bodyLangParam": 1173,
        "forceDoFreeStyle": true,
        "canDoRepeatFreeStyle": false
      },
      {
        "$type": "MoleMole.Config.ConfigDialogInterAction",
        "type": "DIALOG",
        "delayTime": 2.495,
        "aliasList": [
          "1035"
        ],
        "dialogID": 722781801,
        "protectTime": 0.5
      },
      {
        "$type": "MoleMole.Config.ConfigEmoSyncInterAction",
        "type": "EMO_SYNC",
        "delayTime": 2.521,
        "aliasList": [
          "1035"
        ],
        "dataPath": "Cs_Emo_Avatar_Simple_Common_Set/Cs_Emo_Avatar_Talk/Cs_Emo_Avatar_Event/Cs_Emo_RongCaiJi/Cs_Emo_722781801",
        "phonemePath": "",
        "emotionPath": "",
        "mateDataPath": "",
        "matePhonemePath": "",
        "mateEmotionPath": "",
        "dataPathHashList": [
          369128995183,
          76535718988,
          373830637786,
          367783242944
        ]
      },
      {
        "$type": "MoleMole.Config.ConfigSteerInterAction",
        "type": "STEER_TO",
        "delayTime": 3.097,
        "duration": 1.0,
        "aliasList": [
          "10090"
        ],
        "steerType": "ABSOLUTE",
        "steerDir": {
          "x": -3011.696,
          "y": 217.298,
          "z": -4335.619
        },
        "useSteerAnim": true,
        "targetNpcAlias": ""
      },
      {
        "$type": "MoleMole.Config.ConfigLookAtInterAction",
        "type": "LOOK_AT",
        "delayTime": 3.512,
        "aliasList": [
          "10090"
        ],
        "enableHead": true,
        "headTurnTime": 0.5,
        "targetNpcAlias": "Avatar"
      },
      {
        "$type": "MoleMole.Config.ConfigLookAtEyeCtrlInterAction",
        "type": "LOOK_AT_EYECTRL",
        "delayTime": 3.641,
        "aliasList": [
          "10090"
        ],
        "useTargetPos": false,
        "turnTime": 0.1,
        "targetNpcAlias": "",
        "targetPoint": "Face"
      }
    ],
    [
      {
        "$type": "MoleMole.Config.ConfigLookAtInterAction",
        "type": "LOOK_AT",
        "aliasList": [
          "10090"
        ],
        "enableHead": true,
        "headTurnTime": 0.5,
        "targetNpcAlias": "Avatar"
      },
      {
        "$type": "MoleMole.Config.ConfigBodyLangInterAction",
        "type": "BODY_LANG",
        "aliasList": [
          "10090"
        ],
        "bodyLangParam": 1171,
        "forceDoFreeStyle": true,
        "canDoRepeatFreeStyle": false
      },
      {
        "$type": "MoleMole.Config.ConfigLookAtInterAction",
        "type": "LOOK_AT",
        "aliasList": [
          "1035"
        ],
        "enableHead": true,
        "headTurnTime": 0.5,
        "targetNpcAlias": "Avatar"
      },
      {
        "$type": "MoleMole.Config.ConfigEmoSyncInterAction",
        "type": "EMO_SYNC",
        "aliasList": [
          "10090"
        ],
        "dataPath": "Cs_Emo_Avatar_Simple_Common_Set/Cs_Emo_Avatar_Talk/Cs_Emo_Avatar_Event/Cs_Emo_RongCaiJi/Cs_Emo_722781802",
        "phonemePath": "",
        "emotionPath": "",
        "mateDataPath": "",
        "matePhonemePath": "",
        "mateEmotionPath": "",
        "enableBlink": false,
        "dataPathHashList": [
          437072033969,
          722815343179,
          86579516727,
          973446487564
        ]
      },
      {
        "$type": "MoleMole.Config.ConfigDialogInterAction",
        "type": "DIALOG",
        "aliasList": [
          "10090"
        ],
        "dialogID": 722781802,
        "protectTime": 0.5
      },
      {
        "$type": "MoleMole.Config.ConfigCameraMoveInterAction",
        "type": "CAMERA_MOVE",
        "duration": 1.0,
        "camPosOffset": {
          "x": -3009.0,
          "y": 218.5,
          "z": -4337.099
        },
        "camForwardTargetOffset": {
          "x": -3009.871,
          "y": 218.469,
          "z": -4336.608
        },
        "camFov": 20.0,
        "lerpPattern": 6,
        "cameraBlendType": "EaseInOutCubic",
        "cutFrameTrans": {},
        "needZAxisRotate": true,
        "openCameraDither": false,
        "targetNpcAlias": "",
        "closeTreeLeafDither": true
      },
      {
        "$type": "MoleMole.Config.ConfigCameraMoveInterAction",
        "type": "CAMERA_MOVE",
        "delayTime": 0.1,
        "duration": 7.259,
        "camPosOffset": {
          "x": -3009.028,
          "y": 218.508,
          "z": -4337.147
        },
        "camForwardTargetOffset": {
          "x": -3009.899,
          "y": 218.477,
          "z": -4336.656
        },
        "camFov": 20.0,
        "cameraBlendType": "EaseOutQuad",
        "cutFrameTrans": {},
        "needZAxisRotate": true,
        "openCameraDither": false,
        "targetNpcAlias": "",
        "closeTreeLeafDither": true
      },
      {
        "$type": "MoleMole.Config.ConfigLookAtInterAction",
        "type": "LOOK_AT",
        "delayTime": 0.151,
        "aliasList": [
          "1005"
        ],
        "enableHead": true,
        "headTurnTime": 0.5,
        "targetNpcAlias": "10090"
      },
      {
        "$type": "MoleMole.Config.ConfigLookAtInterAction",
        "type": "LOOK_AT",
        "delayTime": 0.258,
        "aliasList": [
          "Avatar"
        ],
        "enableHead": true,
        "useTargetPos": true,
        "enableAbsolute": true,
        "targetPosition": {
          "x": -3010.608,
          "y": 218.37,
          "z": -4335.791
        },
        "headTurnTime": 0.5,
        "targetNpcAlias": "10090",
        "lookAtTargetType": "NONE"
      },
      {
        "$type": "MoleMole.Config.ConfigDialogSelectAction",
        "type": "DIALOG_SELECT",
        "delayTime": 0.4,
        "aliasList": [
          "Avatar"
        ],
        "dialogIDList": [
          722781803
        ],
        "grpIDList": [
          3003016987
        ],
        "useGrpId": true
      },
      {
        "$type": "MoleMole.Config.ConfigBodyLangInterAction",
        "type": "BODY_LANG",
        "delayTime": 1.691,
        "aliasList": [
          "10090"
        ],
        "bodyLangParam": 1190,
        "forceDoFreeStyle": true,
        "canDoRepeatFreeStyle": false
      },
      {
        "$type": "MoleMole.Config.ConfigBodyLangInterAction",
        "type": "BODY_LANG",
        "delayTime": 3.197,
        "aliasList": [
          "10090"
        ],
        "isContinue": true,
        "forceDoFreeStyle": true,
        "canDoRepeatFreeStyle": false
      }
    ],
    [
      {
        "$type": "MoleMole.Config.ConfigDialogInterAction",
        "type": "DIALOG",
        "aliasList": [
          "1035"
        ],
        "dialogID": 722781804,
        "protectTime": 0.5
      },
      {
        "$type": "MoleMole.Config.ConfigBodyLangInterAction",
        "type": "BODY_LANG",
        "aliasList": [
          "1035"
        ],
        "bodyLangParam": 1172,
        "forceDoFreeStyle": true,
        "canDoRepeatFreeStyle": false
      },
      {
        "$type": "MoleMole.Config.ConfigEmoSyncInterAction",
        "type": "EMO_SYNC",
        "aliasList": [
          "1035"
        ],
        "dataPath": "Cs_Emo_Avatar_Simple_Common_Set/Cs_Emo_Avatar_Talk/Cs_Emo_Avatar_Event/Cs_Emo_RongCaiJi/Cs_Emo_722781804",
        "phonemePath": "",
        "emotionPath": "",
        "mateDataPath": "",
        "matePhonemePath": "",
        "mateEmotionPath": "",
        "enableBlink": false,
        "dataPathHashList": [
          832066055601,
          1078135350376,
          699230264068,
          67689073142
        ]
      },
      {
        "$type": "MoleMole.Config.ConfigCameraMoveInterAction",
        "type": "CAMERA_MOVE",
        "duration": 1.0,
        "camPosOffset": {
          "x": -3012.338,
          "y": 218.78,
          "z": -4337.068
        },
        "camForwardTargetOffset": {
          "x": -3011.836,
          "y": 218.71,
          "z": -4336.206
        },
        "camFov": 20.0,
        "lerpPattern": 6,
        "cameraBlendType": "EaseInOutCubic",
        "cutFrameTrans": {},
        "needZAxisRotate": true,
        "openCameraDither": false,
        "targetNpcAlias": "",
        "closeTreeLeafDither": true
      },
      {
        "$type": "MoleMole.Config.ConfigCameraMoveInterAction",
        "type": "CAMERA_MOVE",
        "delayTime": 0.1,
        "duration": 11.303,
        "camPosOffset": {
          "x": -3012.294,
          "y": 218.774,
          "z": -4336.993
        },
        "camForwardTargetOffset": {
          "x": -3011.792,
          "y": 218.704,
          "z": -4336.131
        },
        "camFov": 20.0,
        "cameraBlendType": "EaseOutQuad",
        "cutFrameTrans": {},
        "needZAxisRotate": true,
        "openCameraDither": false,
        "targetNpcAlias": "",
        "closeTreeLeafDither": true
      },
      {
        "$type": "MoleMole.Config.ConfigLookAtInterAction",
        "type": "LOOK_AT",
        "delayTime": 0.194,
        "aliasList": [
          "1005"
        ],
        "enableHead": true,
        "headTurnTime": 0.5,
        "targetNpcAlias": "1035"
      },
      {
        "$type": "MoleMole.Config.ConfigLookAtInterAction",
        "type": "LOOK_AT",
        "delayTime": 0.258,
        "aliasList": [
          "Avatar"
        ],
        "enableHead": true,
        "headTurnTime": 0.5,
        "targetNpcAlias": "1035"
      }
    ],
    [
      {
        "$type": "MoleMole.Config.ConfigBodyLangInterAction",
        "type": "BODY_LANG",
        "aliasList": [
          "1035"
        ],
        "bodyLangParam": 1130,
        "forceDoFreeStyle": true,
        "canDoRepeatFreeStyle": false
      },
      {
        "$type": "MoleMole.Config.ConfigEmoSyncInterAction",
        "type": "EMO_SYNC",
        "aliasList": [
          "1035"
        ],
        "dataPath": "Cs_Emo_Avatar_Simple_Common_Set/Cs_Emo_Avatar_Talk/Cs_Emo_Avatar_Event/Cs_Emo_RongCaiJi/Cs_Emo_722781805",
        "phonemePath": "",
        "emotionPath": "",
        "mateDataPath": "",
        "matePhonemePath": "",
        "mateEmotionPath": "",
        "dataPathHashList": [
          13644898101,
          889659667482,
          812622329929,
          356926607020
        ]
      },
      {
        "$type": "MoleMole.Config.ConfigDialogInterAction",
        "type": "DIALOG",
        "aliasList": [
          "1035"
        ],
        "dialogID": 722781805,
        "protectTime": 0.5
      },
      {
        "$type": "MoleMole.Config.ConfigCameraMoveInterAction",
        "type": "CAMERA_MOVE",
        "duration": 1.0,
        "camPosOffset": {
          "x": -3016.669,
          "y": 221.562,
          "z": -4352.346
        },
        "camForwardTargetOffset": {
          "x": -3016.313,
          "y": 221.418,
          "z": -4351.423
        },
        "camFov": 20.0,
        "lerpPattern": 6,
        "cameraBlendType": "EaseInOutCubic",
        "cutFrameTrans": {},
        "needZAxisRotate": true,
        "openCameraDither": false,
        "targetNpcAlias": "",
        "closeTreeLeafDither": true
      },
      {
        "$type": "MoleMole.Config.ConfigCameraMoveInterAction",
        "type": "CAMERA_MOVE",
        "delayTime": 0.1,
        "duration": 9.367,
        "camPosOffset": {
          "x": -3016.388,
          "y": 221.712,
          "z": -4352.431
        },
        "camForwardTargetOffset": {
          "x": -3016.032,
          "y": 221.568,
          "z": -4351.508
        },
        "camFov": 20.0,
        "cameraBlendType": "EaseOutQuad",
        "cutFrameTrans": {},
        "needZAxisRotate": true,
        "openCameraDither": false,
        "targetNpcAlias": "",
        "closeTreeLeafDither": true
      },
      {
        "$type": "MoleMole.Config.ConfigBodyLangInterAction",
        "type": "BODY_LANG",
        "delayTime": 1.846,
        "aliasList": [
          "1035"
        ],
        "isContinue": true,
        "forceDoFreeStyle": true,
        "canDoRepeatFreeStyle": false
      },
      {
        "$type": "MoleMole.Config.ConfigBodyLangInterAction",
        "type": "BODY_LANG",
        "delayTime": 2.212,
        "aliasList": [
          "1035"
        ],
        "bodyLangParam": 1171,
        "forceDoFreeStyle": true,
        "canDoRepeatFreeStyle": false
      }
    ],
    [
      {
        "$type": "MoleMole.Config.ConfigLookAtInterAction",
        "type": "LOOK_AT",
        "aliasList": [
          "10090"
        ],
        "enableHead": true,
        "useTargetPos": true,
        "enableAbsolute": true,
        "targetPosition": {
          "x": -3010.785,
          "y": 218.693,
          "z": -4334.886
        },
        "headTurnTime": 0.5,
        "targetNpcAlias": "1035",
        "lookAtTargetType": "NONE"
      },
      {
        "$type": "MoleMole.Config.ConfigLookAtInterAction",
        "type": "LOOK_AT",
        "aliasList": [
          "1035"
        ],
        "enableHead": true,
        "useTargetPos": true,
        "enableAbsolute": true,
        "targetPosition": {
          "x": -3010.667,
          "y": 218.399,
          "z": -4335.594
        },
        "headTurnTime": 0.5,
        "targetNpcAlias": "",
        "lookAtTargetType": "NONE"
      },
      {
        "$type": "MoleMole.Config.ConfigEmoSyncInterAction",
        "type": "EMO_SYNC",
        "aliasList": [
          "10090"
        ],
        "dataPath": "Cs_Emo_Avatar_Simple_Common_Set/Cs_Emo_Avatar_Talk/Cs_Emo_Avatar_Event/Cs_Emo_RongCaiJi/Cs_Emo_722781806",
        "phonemePath": "",
        "emotionPath": "",
        "mateDataPath": "",
        "matePhonemePath": "",
        "mateEmotionPath": "",
        "dataPathHashList": [
          372610270149,
          607298745240,
          935416152925,
          275110273334
        ]
      },
      {
        "$type": "MoleMole.Config.ConfigSteerInterAction",
        "type": "STEER_TO",
        "duration": 1.0,
        "aliasList": [
          "10090"
        ],
        "steerType": "ABSOLUTE",
        "steerDir": {
          "x": -3011.055,
          "y": 217.298,
          "z": -4335.218
        },
        "useSteerAnim": true,
        "targetNpcAlias": ""
      },
      {
        "$type": "MoleMole.Config.ConfigCameraMoveInterAction",
        "type": "CAMERA_MOVE",
        "duration": 1.0,
        "camPosOffset": {
          "x": -3011.609,
          "y": 218.429,
          "z": -4337.591
        },
        "camForwardTargetOffset": {
          "x": -3011.227,
          "y": 218.434,
          "z": -4336.667
        },
        "camFov": 20.0,
        "lerpPattern": 6,
        "cameraBlendType": "EaseInOutCubic",
        "cutFrameTrans": {},
        "needZAxisRotate": true,
        "openCameraDither": false,
        "targetNpcAlias": "",
        "closeTreeLeafDither": true
      },
      {
        "$type": "MoleMole.Config.ConfigDialogInterAction",
        "type": "DIALOG",
        "aliasList": [
          "10090"
        ],
        "dialogID": 722781806,
        "protectTime": 5.0,
        "autoTalkUseNewProtectTime": true,
        "autoTalkProtectTime": 5.0
      },
      {
        "$type": "MoleMole.Config.ConfigCameraMoveInterAction",
        "type": "CAMERA_MOVE",
        "delayTime": 0.1,
        "duration": 10.83,
        "camPosOffset": {
          "x": -3010.759,
          "y": 218.462,
          "z": -4337.943
        },
        "camForwardTargetOffset": {
          "x": -3010.377,
          "y": 218.467,
          "z": -4337.019
        },
        "camFov": 20.0,
        "cameraBlendType": "EaseInOutQuint",
        "cutFrameTrans": {},
        "needZAxisRotate": true,
        "openCameraDither": false,
        "targetNpcAlias": "",
        "closeTreeLeafDither": true
      },
      {
        "$type": "MoleMole.Config.ConfigLookAtEyeCtrlInterAction",
        "type": "LOOK_AT_EYECTRL",
        "delayTime": 0.134,
        "aliasList": [
          "1035"
        ],
        "useTargetPos": false,
        "eyeRotateVecLeft": {
          "z": 3.0
        },
        "eyeRotateVecRight": {
          "z": 3.0
        },
        "turnTime": 0.1,
        "targetNpcAlias": "",
        "targetPoint": "Face"
      },
      {
        "$type": "MoleMole.Config.ConfigSteerInterAction",
        "type": "STEER_TO",
        "delayTime": 0.366,
        "duration": 1.0,
        "aliasList": [
          "1035"
        ],
        "steerType": "ABSOLUTE",
        "steerDir": {
          "x": -3010.744,
          "y": 217.298,
          "z": -4335.879
        },
        "useSteerAnim": true,
        "targetNpcAlias": ""
      },
      {
        "$type": "MoleMole.Config.ConfigBodyLangInterAction",
        "type": "BODY_LANG",
        "delayTime": 1.287,
        "aliasList": [
          "10090"
        ],
        "bodyLangParam": 1060,
        "forceDoFreeStyle": true,
        "canDoRepeatFreeStyle": false
      },
      {
        "$type": "MoleMole.Config.ConfigBodyLangInterAction",
        "type": "BODY_LANG",
        "delayTime": 2.792,
        "aliasList": [
          "10090"
        ],
        "isContinue": true,
        "forceDoFreeStyle": true,
        "canDoRepeatFreeStyle": false
      },
      {
        "$type": "MoleMole.Config.ConfigSteerInterAction",
        "type": "STEER_TO",
        "delayTime": 3.06,
        "duration": 1.0,
        "aliasList": [
          "10090"
        ],
        "steerType": "ABSOLUTE",
        "steerDir": {
          "x": -3009.729,
          "y": 217.298,
          "z": -4335.708
        },
        "targetNpcAlias": ""
      },
      {
        "$type": "MoleMole.Config.ConfigSteerInterAction",
        "type": "STEER_TO",
        "delayTime": 3.662,
        "duration": 1.0,
        "aliasList": [
          "1035"
        ],
        "steerType": "ABSOLUTE",
        "steerDir": {
          "x": -3009.382,
          "y": 217.298,
          "z": -4335.147
        },
        "useSteerAnim": true,
        "targetNpcAlias": ""
      },
      {
        "$type": "MoleMole.Config.ConfigLookAtInterAction",
        "type": "LOOK_AT",
        "delayTime": 3.705,
        "aliasList": [
          "10090"
        ],
        "headTurnTime": 0.5,
        "targetNpcAlias": ""
      },
      {
        "$type": "MoleMole.Config.ConfigEmoSyncInterAction",
        "type": "EMO_SYNC",
        "delayTime": 4.052,
        "aliasList": [
          "1035"
        ],
        "dataPath": "",
        "phonemePath": "Cs_Emo_Avatar_Common/Cs_Emo_Avatar_Normal01",
        "emotionPath": "Cs_Emo_Avatar_Common/Cs_Emo_Avatar_Default01_B",
        "mateDataPath": "",
        "matePhonemePath": "",
        "mateEmotionPath": "",
        "phonemePathHashList": [
          47486115231,
          192600119379,
          267713604918,
          969611752301
        ],
        "emotionPathHashList": [
          138354101216,
          512904510258,
          479636551811,
          996333031804
        ]
      },
      {
        "$type": "MoleMole.Config.ConfigMoveToAction",
        "type": "MOVE_TO",
        "delayTime": 4.221,
        "aliasList": [
          "10090"
        ],
        "moveType": "WALK",
        "routeList": [
          {
            "x": -3005.909,
            "y": 217.299,
            "z": -4336.123
          }
        ],
        "exactlyMove": true
      },
      {
        "$type": "MoleMole.Config.ConfigLookAtInterAction",
        "type": "LOOK_AT",
        "delayTime": 4.415,
        "aliasList": [
          "1035"
        ],
        "headTurnTime": 0.5,
        "targetNpcAlias": ""
      },
      {
        "$type": "MoleMole.Config.ConfigMoveToAction",
        "type": "MOVE_TO",
        "delayTime": 4.781,
        "aliasList": [
          "1035"
        ],
        "moveType": "WALK",
        "routeList": [
          {
            "x": -3005.588,
            "y": 217.299,
            "z": -4335.224
          }
        ],
        "exactlyMove": true
      }
    ],
    [
      {
        "$type": "MoleMole.Config.ConfigTimeProtectAction",
        "type": "TIME_PROTECT",
        "duration": 3.5
      },
      {
        "$type": "MoleMole.Config.ConfigDialogInterAction",
        "type": "DIALOG_CLEAR"
      },
      {
        "$type": "MoleMole.Config.ConfigSimpleBlackScreenAction",
        "type": "SIMPLE_BLACK_SCREEN",
        "durationToBlack": 0.5,
        "durationKeepBlack": 3.0,
        "durationFromBlack": 0.5,
        "textMapID": "",
        "useTextFade": true,
        "dialogID": 722781807
      },
      {
        "$type": "MoleMole.Config.ConfigVisibleInterAction",
        "type": "VISIBLE",
        "delayTime": 0.6,
        "aliasList": [
          "10090"
        ]
      },
      {
        "$type": "MoleMole.Config.ConfigVisibleInterAction",
        "type": "VISIBLE",
        "delayTime": 0.6,
        "aliasList": [
          "1035"
        ]
      },
      {
        "$type": "MoleMole.Config.ConfigCameraMoveInterAction",
        "type": "CAMERA_MOVE",
        "delayTime": 1.0,
        "duration": 1.0,
        "camPosOffset": {
          "x": -3002.323,
          "y": 219.085,
          "z": -4335.169
        },
        "camForwardTargetOffset": {
          "x": -3003.318,
          "y": 218.986,
          "z": -4335.196
        },
        "camFov": 20.0,
        "lerpPattern": 6,
        "cameraBlendType": "EaseInOutCubic",
        "cutFrameTrans": {},
        "needZAxisRotate": true,
        "openCameraDither": false,
        "targetNpcAlias": "",
        "closeTreeLeafDither": true
      }
    ],
    [
      {
        "$type": "MoleMole.Config.ConfigLookAtInterAction",
        "type": "LOOK_AT",
        "aliasList": [
          "1005"
        ],
        "headTurnTime": 0.5,
        "targetNpcAlias": ""
      },
      {
        "$type": "MoleMole.Config.ConfigBodyLangInterAction",
        "type": "BODY_LANG",
        "aliasList": [
          "1005"
        ],
        "bodyLangParam": 1170,
        "forceDoFreeStyle": true,
        "canDoRepeatFreeStyle": false
      },
      {
        "$type": "MoleMole.Config.ConfigEmoSyncInterAction",
        "type": "EMO_SYNC",
        "aliasList": [
          "1005"
        ],
        "dataPath": "Cs_Emo_Avatar_Simple_Common_Set/Cs_Emo_Avatar_Talk/Cs_Emo_Avatar_Event/Cs_Emo_RongCaiJi/Cs_Emo_722781808",
        "phonemePath": "",
        "emotionPath": "",
        "mateDataPath": "",
        "matePhonemePath": "",
        "mateEmotionPath": "",
        "dataPathHashList": [
          306643992048,
          108442634670,
          662057758678,
          1068549928576
        ]
      },
      {
        "$type": "MoleMole.Config.ConfigCameraMoveInterAction",
        "type": "CAMERA_MOVE",
        "duration": 11.346,
        "camPosOffset": {
          "x": -3001.713,
          "y": 219.146,
          "z": -4335.152
        },
        "camForwardTargetOffset": {
          "x": -3002.708,
          "y": 219.047,
          "z": -4335.179
        },
        "camFov": 20.0,
        "cameraBlendType": "EaseOutQuad",
        "cutFrameTrans": {},
        "needZAxisRotate": true,
        "openCameraDither": false,
        "targetNpcAlias": "",
        "closeTreeLeafDither": true
      },
      {
        "$type": "MoleMole.Config.ConfigLookAtInterAction",
        "type": "LOOK_AT",
        "aliasList": [
          "Avatar"
        ],
        "enableHead": true,
        "useTargetPos": true,
        "enableAbsolute": true,
        "targetPosition": {
          "x": -3007.109,
          "y": 218.683,
          "z": -4335.625
        },
        "headTurnTime": 0.5,
        "targetNpcAlias": "",
        "lookAtTargetType": "NONE"
      },
      {
        "$type": "MoleMole.Config.ConfigDialogInterAction",
        "type": "DIALOG",
        "delayTime": 0.004,
        "aliasList": [
          "1005"
        ],
        "dialogID": 722781808,
        "protectTime": 0.5
      },
      {
        "$type": "MoleMole.Config.ConfigSteerInterAction",
        "type": "STEER_TO",
        "delayTime": 1.527,
        "duration": 1.0,
        "aliasList": [
          "1005"
        ],
        "steerType": "ABSOLUTE",
        "steerDir": {
          "x": -3011.919,
          "y": 217.298,
          "z": -4335.713
        },
        "targetNpcAlias": ""
      },
      {
        "$type": "MoleMole.Config.ConfigBodyLangInterAction",
        "type": "BODY_LANG",
        "delayTime": 1.613,
        "aliasList": [
          "1005"
        ],
        "isContinue": true,
        "forceDoFreeStyle": true,
        "canDoRepeatFreeStyle": false
      },
      {
        "$type": "MoleMole.Config.ConfigLookAtInterAction",
        "type": "LOOK_AT",
        "delayTime": 1.764,
        "aliasList": [
          "1005"
        ],
        "enableHead": true,
        "headTurnTime": 0.5,
        "targetNpcAlias": "Avatar"
      },
      {
        "$type": "MoleMole.Config.ConfigLookAtInterAction",
        "type": "LOOK_AT",
        "delayTime": 2.103,
        "aliasList": [
          "Avatar"
        ],
        "enableHead": true,
        "headTurnTime": 0.5,
        "targetNpcAlias": "1005"
      },
      {
        "$type": "MoleMole.Config.ConfigBodyLangInterAction",
        "type": "BODY_LANG",
        "delayTime": 2.667,
        "aliasList": [
          "1005"
        ],
        "bodyLangParam": 1100,
        "forceDoFreeStyle": true,
        "canDoRepeatFreeStyle": false
      }
    ],
    [
      {
        "$type": "MoleMole.Config.ConfigTeleportToAction",
        "type": "TELEPORT_TO",
        "aliasList": [
          "1005"
        ],
        "position": {
          "x": -3012.09,
          "y": 217.298,
          "z": -4335.196
        },
        "forward": {
          "x": 0.314,
          "z": -0.949
        },
        "openLongDisTeleport": true
      },
      {
        "$type": "MoleMole.Config.ConfigBodyLangInterAction",
        "type": "BODY_LANG",
        "aliasList": [
          "1005"
        ],
        "bodyLangParam": 1260,
        "forceDoFreeStyle": true,
        "canDoRepeatFreeStyle": false
      },
      {
        "$type": "MoleMole.Config.ConfigEmoSyncInterAction",
        "type": "EMO_SYNC",
        "aliasList": [
          "1005"
        ],
        "dataPath": "Cs_Emo_Avatar_Simple_Common_Set/Cs_Emo_Avatar_Talk/Cs_Emo_Avatar_Event/Cs_Emo_RongCaiJi/Cs_Emo_722781809",
        "phonemePath": "",
        "emotionPath": "",
        "mateDataPath": "",
        "matePhonemePath": "",
        "mateEmotionPath": "",
        "dataPathHashList": [
          873725646335,
          1010883008117,
          779790211083,
          132873426447
        ]
      },
      {
        "$type": "MoleMole.Config.ConfigLookAtInterAction",
        "type": "LOOK_AT",
        "aliasList": [
          "1005"
        ],
        "enableHead": true,
        "headTurnTime": 0.5,
        "targetNpcAlias": "Avatar"
      },
      {
        "$type": "MoleMole.Config.ConfigLookAtInterAction",
        "type": "LOOK_AT",
        "aliasList": [
          "Avatar"
        ],
        "enableHead": true,
        "headTurnTime": 0.5,
        "targetNpcAlias": "1005"
      },
      {
        "$type": "MoleMole.Config.ConfigCameraMoveInterAction",
        "type": "CAMERA_MOVE",
        "duration": 1.0,
        "camPosOffset": {
          "x": -3010.74,
          "y": 218.899,
          "z": -4336.916
        },
        "camForwardTargetOffset": {
          "x": -3011.434,
          "y": 218.728,
          "z": -4336.216
        },
        "camFov": 20.0,
        "lerpPattern": 6,
        "cameraBlendType": "EaseInOutCubic",
        "cutFrameTrans": {},
        "needZAxisRotate": true,
        "openCameraDither": false,
        "targetNpcAlias": "",
        "closeTreeLeafDither": true
      },
      {
        "$type": "MoleMole.Config.ConfigDialogInterAction",
        "type": "DIALOG",
        "aliasList": [
          "1005"
        ],
        "dialogID": 722781809,
        "protectTime": 0.5
      },
      {
        "$type": "MoleMole.Config.ConfigCameraMoveInterAction",
        "type": "CAMERA_MOVE",
        "delayTime": 0.1,
        "duration": 10.593,
        "camPosOffset": {
          "x": -3010.712,
          "y": 218.904,
          "z": -4336.887
        },
        "camForwardTargetOffset": {
          "x": -3011.406,
          "y": 218.733,
          "z": -4336.188
        },
        "camFov": 20.0,
        "cameraBlendType": "EaseOutQuad",
        "cutFrameTrans": {},
        "needZAxisRotate": true,
        "openCameraDither": false,
        "targetNpcAlias": "",
        "closeTreeLeafDither": true
      },
      {
        "$type": "MoleMole.Config.ConfigBodyLangInterAction",
        "type": "BODY_LANG",
        "delayTime": 2.206,
        "aliasList": [
          "1005"
        ],
        "bodyLangParam": 1170,
        "forceDoFreeStyle": true,
        "canDoRepeatFreeStyle": false
      },
      {
        "$type": "MoleMole.Config.ConfigBodyLangInterAction",
        "type": "BODY_LANG",
        "delayTime": 4.056,
        "aliasList": [
          "1005"
        ],
        "isContinue": true,
        "forceDoFreeStyle": true,
        "canDoRepeatFreeStyle": false
      }
    ],
    [
      {
        "$type": "MoleMole.Config.ConfigDialogInterAction",
        "type": "DIALOG_CLEAR",
        "dialogID": 722781809
      },
      {
        "$type": "MoleMole.Config.ConfigTimeProtectAction",
        "type": "TIME_PROTECT",
        "duration": 0.7
      },
      {
        "$type": "MoleMole.Config.ConfigSimpleBlackScreenAction",
        "type": "SIMPLE_BLACK_SCREEN",
        "durationToBlack": 0.5,
        "durationKeepBlack": 1.0,
        "durationFromBlack": 0.5,
        "textMapID": ""
      },
      {
        "$type": "MoleMole.Config.ConfigHideWidgetPet",
        "type": "HIDE_WIDGET_PET",
        "delayTime": 0.5
      },
      {
        "$type": "MoleMole.Config.ConfigCameraMoveInterAction",
        "type": "CAMERA_MOVE",
        "delayTime": 0.6,
        "duration": 0.1,
        "camPosOffset": {
          "x": -3013.693,
          "y": 218.705,
          "z": -4337.616
        },
        "camForwardTargetOffset": {
          "x": -3012.977,
          "y": 218.478,
          "z": -4336.957
        },
        "lerpPattern": 6,
        "cameraBlendType": "EaseInOutCubic",
        "cutFrameTrans": {},
        "needZAxisRotate": true,
        "openCameraDither": false,
        "targetNpcAlias": "",
        "closeTreeLeafDither": true
      }
    ]
  ],
  "groupId": [
    {
      "grpId": 3003016984,
      "nextGrpId": 3003016985
    },
    {
      "index": 1,
      "grpId": 3003016985,
      "nextGrpId": 3003016986
    },
    {
      "index": 2,
      "grpId": 3003016986,
      "nextGrpId": 3003016987
    },
    {
      "index": 3,
      "grpId": 3003016987,
      "nextGrpId": 3003016988
    },
    {
      "index": 4,
      "grpId": 3003016988,
      "nextGrpId": 3003016989
    },
    {
      "index": 5,
      "grpId": 3003016989,
      "nextGrpId": 3003016990
    },
    {
      "index": 6,
      "grpId": 3003016990,
      "nextGrpId": 3003016991
    },
    {
      "index": 7,
      "grpId": 3003016991,
      "nextGrpId": 3003016992
    },
    {
      "index": 8,
      "grpId": 3003016992,
      "nextGrpId": 2899213336
    },
    {
      "index": 9,
      "grpId": 2899213336,
      "nextGrpId": 2899213337
    }
  ],
  "freeStyleDic": {
    "10090": [
      1171,
      1190,
      1060
    ],
    "1035": [
      4031,
      1173,
      1172,
      1130,
      1171
    ]
  }
}