{
  "luaDataPath": "",
  "dontUseDefaultFinish": true,
  "entityBan": "",
  "disableNpcLod": true,
  "startFade": {
    "startFadeOutDuration": 0.0
  },
  "endFade": {
    "startFadeOutDuration": 0.0
  },
  "actors": [
    {
      "alias": "Avatar",
      "visible": true,
      "bornPointName": ""
    },
    {
      "configID": 1013,
      "alias": "1013",
      "visible": true,
      "bornPointName": ""
    },
    {
      "configID": 12038,
      "alias": "12038",
      "visible": true,
      "bornPointName": ""
    }
  ],
  "group": [
    [
      {
        "$type": "MoleMole.Config.ConfigCameraMoveInterAction",
        "type": "CAMERA_MOVE",
        "duration": 0.1,
        "camPosOffset": {
          "x": -2982.4038,
          "y": 207.37746,
          "z": -3977.755
        },
        "camForwardTargetOffset": {
          "x": -2981.647,
          "y": 207.4524,
          "z": -3978.4043
        },
        "camFov": 30.0,
        "lerpPattern": 6,
        "cameraBlendType": "EaseInOutCubic",
        "cutFrameTrans": {},
        "openCameraDither": false,
        "targetNpcAlias": ""
      },
      {
        "$type": "MoleMole.Config.ConfigTeleportToAction",
        "type": "TELEPORT_TO",
        "aliasList": [
          "Avatar"
        ],
        "position": {
          "x": -2980.9202,
          "y": 206.22089,
          "z": -3978.6077
        },
        "forward": {
          "x": -0.9999967,
          "z": 0.0025408864
        }
      },
      {
        "$type": "MoleMole.Config.ConfigLookAtInterAction",
        "type": "LOOK_AT",
        "aliasList": [
          "Avatar"
        ],
        "enableHead": true,
        "useTargetPos": true,
        "enableAbsolute": true,
        "targetPosition": {
          "x": -2981.4146,
          "y": 207.5676,
          "z": -3978.9678
        },
        "headTurnTime": 0.5,
        "targetNpcAlias": ""
      },
      {
        "$type": "MoleMole.Config.ConfigDialogInterAction",
        "type": "DIALOG",
        "aliasList": [
          "1013"
        ],
        "dialogID": 120081202,
        "protectTime": 0.5
      },
      {
        "$type": "MoleMole.Config.ConfigBodyLangInterAction",
        "type": "BODY_LANG",
        "aliasList": [
          "1013"
        ],
        "bodyLangParam": 1130,
        "forceDoFreeStyle": true,
        "canDoRepeatFreeStyle": false
      },
      {
        "$type": "MoleMole.Config.ConfigTeleportToAction",
        "type": "TELEPORT_TO",
        "aliasList": [
          "1013"
        ],
        "position": {
          "x": -2981.344,
          "y": 206.2576,
          "z": -3979.216
        },
        "forward": {
          "x": 0.5349121,
          "z": 0.7080078
        }
      },
      {
        "$type": "MoleMole.Config.ConfigLookAtInterAction",
        "type": "LOOK_AT",
        "aliasList": [
          "1013"
        ],
        "enableHead": true,
        "useTargetPos": true,
        "enableAbsolute": true,
        "targetPosition": {
          "x": -2980.967,
          "y": 207.55441,
          "z": -3978.602
        },
        "headTurnTime": 0.4,
        "targetNpcAlias": ""
      },
      {
        "$type": "MoleMole.Config.ConfigEmoSyncInterAction",
        "type": "EMO_SYNC",
        "aliasList": [
          "1013"
        ],
        "dataPath": "Cs_Emo_Avatar_Simple_Common_Set/Cs_Emo_Avatar_Talk/Cs_Emo_Avatar_PersonalLine/Cs_Emo_Avatar_Ayaka/Cs_Emo_120081202",
        "phonemePath": "",
        "emotionPath": "",
        "mateDataPath": "",
        "matePhonemePath": "",
        "mateEmotionPath": "",
        "dataPathHashList": [
          625309399870,
          506692700991,
          684346005440,
          408680707429
        ]
      },
      {
        "$type": "MoleMole.Config.ConfigTeleportToAction",
        "type": "TELEPORT_TO",
        "aliasList": [
          "12038"
        ],
        "position": {
          "x": -2982.8054,
          "y": 206.3702,
          "z": -3978.997
        },
        "forward": {
          "x": 0.9389553,
          "z": 0.3440392
        }
      },
      {
        "$type": "MoleMole.Config.ConfigLookAtInterAction",
        "type": "LOOK_AT",
        "aliasList": [
          "12038"
        ],
        "enableHead": true,
        "useTargetPos": true,
        "enableAbsolute": true,
        "targetPosition": {
          "x": -2981.3398,
          "y": 207.50638,
          "z": -3979.4194
        },
        "headTurnTime": 0.5,
        "targetNpcAlias": ""
      },
      {
        "$type": "MoleMole.Config.ConfigLookAtEyeCtrlInterAction",
        "type": "LOOK_AT_EYECTRL",
        "aliasList": [
          "12038"
        ],
        "useTargetPos": false,
        "eyeRotateVecLeft": {
          "z": 4.0
        },
        "eyeRotateVecRight": {
          "z": 4.0
        },
        "turnTime": 0.3,
        "targetNpcAlias": "",
        "targetPoint": "Face"
      }
    ],
    [
      {
        "$type": "MoleMole.Config.ConfigCameraMoveInterAction",
        "type": "CAMERA_MOVE",
        "delayTime": 0.34829438,
        "duration": 0.1,
        "camPosOffset": {
          "x": -2980.3901,
          "y": 207.4997,
          "z": -3978.104
        },
        "camForwardTargetOffset": {
          "x": -2981.2336,
          "y": 207.59256,
          "z": -3978.6333
        },
        "camFov": 30.0,
        "lerpPattern": 6,
        "cameraBlendType": "EaseInOutCubic",
        "cutFrameTrans": {},
        "openCameraDither": false,
        "targetNpcAlias": ""
      },
      {
        "$type": "MoleMole.Config.ConfigLookAtInterAction",
        "type": "LOOK_AT",
        "delayTime": 0.1833127,
        "aliasList": [
          "Avatar"
        ],
        "enableHead": true,
        "useTargetPos": true,
        "enableAbsolute": true,
        "targetPosition": {
          "x": -2982.9504,
          "y": 207.80884,
          "z": -3979.0957
        },
        "headTurnTime": 0.5,
        "targetNpcAlias": ""
      },
      {
        "$type": "MoleMole.Config.ConfigBodyLangInterAction",
        "type": "BODY_LANG",
        "aliasList": [
          "1013"
        ],
        "isContinue": true,
        "forceDoFreeStyle": true,
        "canDoRepeatFreeStyle": false
      },
      {
        "$type": "MoleMole.Config.ConfigSteerInterAction",
        "type": "STEER_TO",
        "delayTime": 0.71829176,
        "duration": 0.8,
        "aliasList": [
          "1013"
        ],
        "steerType": "ABSOLUTE",
        "steerDir": {
          "x": -2983.0713,
          "y": 206.2576,
          "z": -3978.9673
        },
        "useSteerAnim": true,
        "targetNpcAlias": ""
      },
      {
        "$type": "MoleMole.Config.ConfigLookAtInterAction",
        "type": "LOOK_AT",
        "delayTime": 1.4939991,
        "aliasList": [
          "1013"
        ],
        "enableHead": true,
        "useTargetPos": true,
        "enableAbsolute": true,
        "targetPosition": {
          "x": -2982.9504,
          "y": 207.80884,
          "z": -3979.0957
        },
        "headTurnTime": 0.3,
        "targetNpcAlias": ""
      },
      {
        "$type": "MoleMole.Config.ConfigLookAtInterAction",
        "type": "LOOK_AT",
        "delayTime": 0.64159477,
        "aliasList": [
          "1013"
        ],
        "enableHead": true,
        "useTargetPos": true,
        "enableAbsolute": true,
        "targetPosition": {
          "x": -2982.9504,
          "y": 207.80884,
          "z": -3979.0957
        },
        "headTurnTime": 0.5,
        "targetNpcAlias": ""
      },
      {
        "$type": "MoleMole.Config.ConfigEmoSyncInterAction",
        "type": "EMO_SYNC",
        "delayTime": 0.75466645,
        "aliasList": [
          "1013"
        ],
        "dataPath": "",
        "phonemePath": "Cs_Emo_Avatar_Common/Cs_Emo_Avatar_Default01",
        "emotionPath": "Cs_Emo_Avatar_Common/Cs_Emo_Avatar_Normal01_B",
        "mateDataPath": "",
        "matePhonemePath": "",
        "mateEmotionPath": "",
        "phonemePathHashList": [
          1065335969186,
          117366768616,
          743255274774,
          441582405585
        ],
        "emotionPathHashList": [
          632876724316,
          506607825209,
          214245330246,
          731774299883
        ]
      },
      {
        "$type": "MoleMole.Config.ConfigDialogInterAction",
        "type": "DIALOG",
        "aliasList": [
          "12038"
        ],
        "dialogID": 120081203,
        "protectTime": 1.0
      },
      {
        "$type": "MoleMole.Config.ConfigLookAtInterAction",
        "type": "LOOK_AT",
        "aliasList": [
          "12038"
        ],
        "enableHead": true,
        "useTargetPos": true,
        "enableAbsolute": true,
        "targetPosition": {
          "x": -2981.359,
          "y": 207.50638,
          "z": -3978.8428
        },
        "headTurnTime": 0.5,
        "targetNpcAlias": ""
      },
      {
        "$type": "MoleMole.Config.ConfigBodyLangInterAction",
        "type": "BODY_LANG",
        "aliasList": [
          "12038"
        ],
        "bodyLangParam": 1260,
        "forceDoFreeStyle": true,
        "canDoRepeatFreeStyle": false
      },
      {
        "$type": "MoleMole.Config.ConfigBodyLangInterAction",
        "type": "BODY_LANG",
        "delayTime": 3.8529406,
        "aliasList": [
          "12038"
        ],
        "bodyLangParam": 1172,
        "forceDoFreeStyle": true,
        "canDoRepeatFreeStyle": false
      },
      {
        "$type": "MoleMole.Config.ConfigBodyLangInterAction",
        "type": "BODY_LANG",
        "delayTime": 5.3927693,
        "aliasList": [
          "12038"
        ],
        "bodyLangParam": 1173,
        "forceDoFreeStyle": true,
        "canDoRepeatFreeStyle": false
      },
      {
        "$type": "MoleMole.Config.ConfigBodyLangInterAction",
        "type": "BODY_LANG",
        "delayTime": 8.664902,
        "aliasList": [
          "12038"
        ],
        "bodyLangParam": 1130,
        "forceDoFreeStyle": true,
        "canDoRepeatFreeStyle": false
      },
      {
        "$type": "MoleMole.Config.ConfigEmoSyncInterAction",
        "type": "EMO_SYNC",
        "aliasList": [
          "12038"
        ],
        "dataPath": "Cs_Emo_Avatar_Simple_Common_Set/Cs_Emo_Avatar_Talk/Cs_Emo_Avatar_PersonalLine/Cs_Emo_Avatar_Ayaka/Cs_Emo_120081203",
        "phonemePath": "",
        "emotionPath": "",
        "mateDataPath": "",
        "matePhonemePath": "",
        "mateEmotionPath": "",
        "dataPathHashList": [
          466972199558,
          329974263835,
          1095991978832,
          33148985693
        ]
      }
    ],
    [
      {
        "$type": "MoleMole.Config.ConfigLookAtInterAction",
        "type": "LOOK_AT",
        "aliasList": [
          "Avatar"
        ],
        "enableHead": true,
        "useTargetPos": true,
        "enableAbsolute": true,
        "targetPosition": {
          "x": -2981.4146,
          "y": 207.5676,
          "z": -3978.9678
        },
        "headTurnTime": 0.5,
        "targetNpcAlias": ""
      },
      {
        "$type": "MoleMole.Config.ConfigTeleportToAction",
        "type": "TELEPORT_TO",
        "aliasList": [
          "Avatar"
        ],
        "position": {
          "x": -2980.9202,
          "y": 206.22089,
          "z": -3978.6077
        },
        "forward": {
          "x": -0.9999967,
          "z": 0.0025408864
        }
      },
      {
        "$type": "MoleMole.Config.ConfigLookAtInterAction",
        "type": "LOOK_AT",
        "aliasList": [
          "1013"
        ],
        "enableHead": true,
        "useTargetPos": true,
        "enableAbsolute": true,
        "targetPosition": {
          "x": -2980.967,
          "y": 207.69212,
          "z": -3978.602
        },
        "headTurnTime": 0.4,
        "targetNpcAlias": ""
      },
      {
        "$type": "MoleMole.Config.ConfigTeleportToAction",
        "type": "TELEPORT_TO",
        "aliasList": [
          "1013"
        ],
        "position": {
          "x": -2981.344,
          "y": 206.2576,
          "z": -3979.216
        },
        "forward": {
          "x": 0.5349121,
          "z": 0.7080078
        }
      },
      {
        "$type": "MoleMole.Config.ConfigLookAtInterAction",
        "type": "LOOK_AT",
        "aliasList": [
          "12038"
        ],
        "enableHead": true,
        "useTargetPos": true,
        "enableAbsolute": true,
        "targetPosition": {
          "x": -2981.3398,
          "y": 207.50638,
          "z": -3979.4194
        },
        "headTurnTime": 0.5,
        "targetNpcAlias": ""
      },
      {
        "$type": "MoleMole.Config.ConfigTeleportToAction",
        "type": "TELEPORT_TO",
        "aliasList": [
          "12038"
        ],
        "position": {
          "x": -2982.8054,
          "y": 206.3702,
          "z": -3978.997
        },
        "forward": {
          "x": 0.9389553,
          "z": 0.3440392
        }
      }
    ]
  ],
  "groupId": [
    {
      "grpId": 608842972,
      "nextGrpId": 608842973
    },
    {
      "index": 1,
      "grpId": 608842973,
      "nextGrpId": 608842974
    },
    {
      "index": 2,
      "grpId": 608842974,
      "nextGrpId": 608842975
    }
  ],
  "freeStyleDic": {
    "1013": [
      1130
    ],
    "12038": [
      1260,
      1172,
      1173,
      1130
    ]
  }
}