{
  "luaDataPath": "",
  "startBlackKeepTime": 0.1,
  "entityBan": "",
  "startFade": {
    "startFadeInDuration": 0.3,
    "startFadeOutDuration": 0.3
  },
  "endFade": {
    "startFadeOutDuration": 0.0
  },
  "actors": [
    {
      "alias": "Avatar",
      "visible": true,
      "bornPointName": "Q38906Player"
    },
    {
      "configID": 1001,
      "alias": "1001",
      "visible": true,
      "bornPointName": "Q389VentiPos2"
    },
    {
      "configID": 1009,
      "alias": "1009",
      "visible": true,
      "bornPointName": "Q389DilucPos2"
    },
    {
      "configID": 1006,
      "alias": "1006",
      "visible": true,
      "bornPointName": "Q389QinPos2"
    },
    {
      "configID": 1005,
      "alias": "1005",
      "visible": true,
      "bornPointName": "Q38906Paimon"
    }
  ],
  "group": [
    [
      {
        "$type": "MoleMole.Config.ConfigCameraMoveInterAction",
        "type": "CAMERA_MOVE",
        "duration": 1.0,
        "camPosOffset": {
          "x": 2663.2852,
          "y": 302.40338,
          "z": 119.66191
        },
        "camForwardTargetOffset": {
          "x": 2662.3032,
          "y": 302.22183,
          "z": 119.609955
        },
        "camFov": 25.0,
        "lerpRatio": 6.0,
        "lerpPattern": 6,
        "cutFrameTrans": {},
        "targetNpcAlias": ""
      },
      {
        "$type": "MoleMole.Config.ConfigCameraMoveInterAction",
        "type": "CAMERA_MOVE",
        "delayTime": 0.1,
        "duration": 8.0,
        "camPosOffset": {
          "x": 2663.3142,
          "y": 302.15015,
          "z": 119.83827
        },
        "camForwardTargetOffset": {
          "x": 2662.3267,
          "y": 302.01004,
          "z": 119.76519
        },
        "camFov": 25.0,
        "lerpRatio": 6.0,
        "cameraBlendType": "EaseInOutQuad",
        "cutFrameTrans": {},
        "targetNpcAlias": ""
      },
      {
        "$type": "MoleMole.Config.ConfigCameraDOFAction",
        "type": "CAMERA_DOF",
        "enabled": true,
        "focusDistance": 5.0,
        "focusRange": 8.0,
        "quality": 3
      },
      {
        "$type": "MoleMole.Config.ConfigLookAtInterAction",
        "type": "LOOK_AT",
        "aliasList": [
          "Avatar"
        ],
        "enableHead": true,
        "useTargetPos": true,
        "enableAbsolute": true,
        "targetPosition": {
          "x": 2657.7314,
          "y": 302.1162,
          "z": 119.14318
        },
        "headTurnTime": 0.1,
        "targetNpcAlias": ""
      },
      {
        "$type": "MoleMole.Config.ConfigDialogSelectAction",
        "type": "DIALOG_SELECT",
        "delayTime": 1.7500014,
        "aliasList": [
          "Avatar"
        ],
        "dialogIDList": [
          3930102,
          3930103
        ],
        "grpIDList": [
          3162378951,
          3162378951
        ],
        "useGrpId": true
      },
      {
        "$type": "MoleMole.Config.ConfigDialogInterAction",
        "type": "DIALOG",
        "delayTime": 0.3,
        "aliasList": [
          "1001"
        ],
        "dialogID": 3930101,
        "protectTime": 2.880666
      },
      {
        "$type": "MoleMole.Config.ConfigLookAtInterAction",
        "type": "LOOK_AT",
        "aliasList": [
          "1001"
        ],
        "enableHead": true,
        "useTargetPos": true,
        "enableAbsolute": true,
        "targetPosition": {
          "x": 2659.83,
          "y": 302.0415,
          "z": 119.84459
        },
        "headTurnTime": 0.1,
        "targetNpcAlias": ""
      },
      {
        "$type": "MoleMole.Config.ConfigBodyLangInterAction",
        "type": "BODY_LANG",
        "aliasList": [
          "1001"
        ],
        "bodyLangParam": 1180
      },
      {
        "$type": "MoleMole.Config.ConfigBodyLangInterAction",
        "type": "BODY_LANG",
        "delayTime": 2.780666,
        "aliasList": [
          "1001"
        ],
        "isContinue": true
      },
      {
        "$type": "MoleMole.Config.ConfigEmoSyncInterAction",
        "type": "EMO_SYNC",
        "delayTime": 0.3,
        "aliasList": [
          "1001"
        ],
        "dataPath": "Cs_Emo_Avatar_Simple_Common_Set/Cs_Emo_Avatar_Talk/Cs_Emo_Avatar_MainLine/Cs_Emo_Avatar_MengDe/Cs_Emo_3930101",
        "phonemePath": "",
        "emotionPath": "",
        "mateDataPath": "",
        "matePhonemePath": "",
        "mateEmotionPath": "",
        "dataPathHashList": [
          675197526137,
          1055027853891,
          668289435706,
          772358955611
        ]
      },
      {
        "$type": "MoleMole.Config.ConfigLookAtInterAction",
        "type": "LOOK_AT",
        "aliasList": [
          "1009"
        ],
        "enableHead": true,
        "headRotateVec": {
          "x": 346.48395,
          "y": 13.130137
        },
        "headTurnTime": 0.1,
        "targetNpcAlias": ""
      },
      {
        "$type": "MoleMole.Config.ConfigBodyLangInterAction",
        "type": "BODY_LANG",
        "aliasList": [
          "1009"
        ],
        "bodyLangParam": 1120
      },
      {
        "$type": "MoleMole.Config.ConfigLookAtInterAction",
        "type": "LOOK_AT",
        "aliasList": [
          "1006"
        ],
        "enableHead": true,
        "useTargetPos": true,
        "enableAbsolute": true,
        "targetPosition": {
          "x": 2657.7314,
          "y": 302.1162,
          "z": 119.14318
        },
        "headTurnTime": 0.1,
        "targetNpcAlias": ""
      },
      {
        "$type": "MoleMole.Config.ConfigLookAtInterAction",
        "type": "LOOK_AT",
        "aliasList": [
          "1005"
        ],
        "enableHead": true,
        "useTargetPos": true,
        "enableAbsolute": true,
        "targetPosition": {
          "x": 2657.7314,
          "y": 302.1162,
          "z": 119.14318
        },
        "headTurnTime": 0.1,
        "targetNpcAlias": ""
      }
    ],
    [
      {
        "$type": "MoleMole.Config.ConfigCameraMoveInterAction",
        "type": "CAMERA_MOVE",
        "duration": 1.0,
        "camPosOffset": {
          "x": 2659.4175,
          "y": 301.89825,
          "z": 119.750404
        },
        "camForwardTargetOffset": {
          "x": 2658.4727,
          "y": 301.82077,
          "z": 119.43231
        },
        "camFov": 30.0,
        "lerpPattern": 6,
        "cameraBlendType": "EaseInOutCubic",
        "cutFrameTrans": {},
        "targetNpcAlias": ""
      },
      {
        "$type": "MoleMole.Config.ConfigCameraDOFAction",
        "type": "CAMERA_DOF",
        "enabled": true,
        "focusDistance": 2.0,
        "focusRange": 3.0,
        "quality": 3
      },
      {
        "$type": "MoleMole.Config.ConfigDialogInterAction",
        "type": "DIALOG",
        "aliasList": [
          "1001"
        ],
        "dialogID": 3930104,
        "protectTime": 2.205666
      },
      {
        "$type": "MoleMole.Config.ConfigBodyLangInterAction",
        "type": "BODY_LANG",
        "aliasList": [
          "1001"
        ],
        "bodyLangParam": 1170
      },
      {
        "$type": "MoleMole.Config.ConfigBodyLangInterAction",
        "type": "BODY_LANG",
        "delayTime": 2.1056662,
        "aliasList": [
          "1001"
        ],
        "isContinue": true
      },
      {
        "$type": "MoleMole.Config.ConfigEmoSyncInterAction",
        "type": "EMO_SYNC",
        "aliasList": [
          "1001"
        ],
        "dataPath": "Cs_Emo_Avatar_Simple_Common_Set/Cs_Emo_Avatar_Talk/Cs_Emo_Avatar_MainLine/Cs_Emo_Avatar_MengDe/Cs_Emo_3930104",
        "phonemePath": "",
        "emotionPath": "",
        "mateDataPath": "",
        "matePhonemePath": "",
        "mateEmotionPath": "",
        "dataPathHashList": [
          598940320809,
          297468591413,
          117000782756,
          720694268183
        ]
      }
    ],
    [
      {
        "$type": "MoleMole.Config.ConfigCameraMoveInterAction",
        "type": "CAMERA_MOVE",
        "duration": 1.0,
        "camPosOffset": {
          "x": 2659.907,
          "y": 302.08075,
          "z": 119.94816
        },
        "camForwardTargetOffset": {
          "x": 2658.9216,
          "y": 301.92285,
          "z": 119.88236
        },
        "camFov": 32.0,
        "cameraBlendType": "EaseInOutQuart",
        "cutFrameTrans": {},
        "targetNpcAlias": ""
      },
      {
        "$type": "MoleMole.Config.ConfigCameraDOFAction",
        "type": "CAMERA_DOF",
        "duration": 1.0,
        "enabled": true,
        "focusDistance": 3.0,
        "focusRange": 3.0,
        "quality": 3
      },
      {
        "$type": "MoleMole.Config.ConfigLookAtInterAction",
        "type": "LOOK_AT",
        "delayTime": 0.5250005,
        "aliasList": [
          "Avatar"
        ],
        "enableHead": true,
        "useTargetPos": true,
        "enableAbsolute": true,
        "targetPosition": {
          "x": 2657.6443,
          "y": 302.1969,
          "z": 120.384705
        },
        "headTurnTime": 0.3,
        "targetNpcAlias": ""
      },
      {
        "$type": "MoleMole.Config.ConfigLookAtInterAction",
        "type": "LOOK_AT",
        "delayTime": 0.36666715,
        "aliasList": [
          "1001"
        ],
        "enableHead": true,
        "useTargetPos": true,
        "enableAbsolute": true,
        "targetPosition": {
          "x": 2657.6443,
          "y": 302.1969,
          "z": 120.23255
        },
        "headTurnTime": 0.3,
        "targetNpcAlias": ""
      },
      {
        "$type": "MoleMole.Config.ConfigDialogInterAction",
        "type": "DIALOG",
        "aliasList": [
          "1006"
        ],
        "dialogID": 3930105,
        "protectTime": 0.7916671
      },
      {
        "$type": "MoleMole.Config.ConfigBodyLangInterAction",
        "type": "BODY_LANG",
        "aliasList": [
          "1006"
        ],
        "bodyLangParam": 1130
      },
      {
        "$type": "MoleMole.Config.ConfigEmoSyncInterAction",
        "type": "EMO_SYNC",
        "aliasList": [
          "1006"
        ],
        "dataPath": "Cs_Emo_Avatar_Simple_Common_Set/Cs_Emo_Avatar_Talk/Cs_Emo_Avatar_MainLine/Cs_Emo_Avatar_MengDe/Cs_Emo_3930105",
        "phonemePath": "",
        "emotionPath": "",
        "mateDataPath": "",
        "matePhonemePath": "",
        "mateEmotionPath": "",
        "dataPathHashList": [
          807240109113,
          840861628017,
          690007774434,
          549476698704
        ]
      },
      {
        "$type": "MoleMole.Config.ConfigLookAtInterAction",
        "type": "LOOK_AT",
        "delayTime": 0.6916671,
        "aliasList": [
          "1005"
        ],
        "enableHead": true,
        "useTargetPos": true,
        "enableAbsolute": true,
        "targetPosition": {
          "x": 2657.6443,
          "y": 302.1969,
          "z": 120.384705
        },
        "headTurnTime": 0.3,
        "targetNpcAlias": ""
      }
    ],
    [
      {
        "$type": "MoleMole.Config.ConfigCameraMoveInterAction",
        "type": "CAMERA_MOVE",
        "delayTime": 0.34430012,
        "duration": 3.0,
        "camPosOffset": {
          "x": 2659.7764,
          "y": 302.01654,
          "z": 119.89791
        },
        "camForwardTargetOffset": {
          "x": 2658.8113,
          "y": 301.93008,
          "z": 120.14562
        },
        "camFov": 25.0,
        "cameraBlendType": "EaseInOutQuad",
        "cutFrameTrans": {},
        "targetNpcAlias": ""
      },
      {
        "$type": "MoleMole.Config.ConfigCameraDOFAction",
        "type": "CAMERA_DOF",
        "delayTime": 0.3443001,
        "duration": 3.0,
        "enabled": true,
        "focusDistance": 2.0,
        "focusRange": 3.0,
        "quality": 3
      },
      {
        "$type": "MoleMole.Config.ConfigDialogInterAction",
        "type": "DIALOG",
        "aliasList": [
          "1006"
        ],
        "dialogID": 3930106,
        "protectTime": 0.44430012
      },
      {
        "$type": "MoleMole.Config.ConfigLookAtInterAction",
        "type": "LOOK_AT",
        "aliasList": [
          "1006"
        ],
        "enableHead": true,
        "useTargetPos": true,
        "enableAbsolute": true,
        "targetPosition": {
          "x": 2659.83,
          "y": 302.0415,
          "z": 119.84459
        },
        "headTurnTime": 0.3,
        "targetNpcAlias": ""
      },
      {
        "$type": "MoleMole.Config.ConfigBodyLangInterAction",
        "type": "BODY_LANG",
        "aliasList": [
          "1006"
        ],
        "isContinue": true
      },
      {
        "$type": "MoleMole.Config.ConfigEmoSyncInterAction",
        "type": "EMO_SYNC",
        "aliasList": [
          "1006"
        ],
        "dataPath": "Cs_Emo_Avatar_Simple_Common_Set/Cs_Emo_Avatar_Talk/Cs_Emo_Avatar_MainLine/Cs_Emo_Avatar_MengDe/Cs_Emo_3930106",
        "phonemePath": "",
        "emotionPath": "",
        "mateDataPath": "",
        "matePhonemePath": "",
        "mateEmotionPath": "",
        "dataPathHashList": [
          566813591166,
          479105271316,
          120197085233,
          617863918184
        ]
      }
    ],
    [
      {
        "$type": "MoleMole.Config.ConfigDialogSelectAction",
        "type": "DIALOG_SELECT",
        "delayTime": 0.8833333,
        "aliasList": [
          "Avatar"
        ],
        "dialogIDList": [
          3930108,
          3930109
        ],
        "grpIDList": [
          3162378955,
          3162378955
        ],
        "useGrpId": true
      },
      {
        "$type": "MoleMole.Config.ConfigEmoSyncInterAction",
        "type": "EMO_SYNC",
        "aliasList": [
          "1001"
        ],
        "dataPath": "Cs_Emo_Avatar_Simple_Common_Set/Cs_Emo_Avatar_Common_Normal",
        "phonemePath": "",
        "emotionPath": "",
        "mateDataPath": "",
        "matePhonemePath": "",
        "mateEmotionPath": "",
        "dataPathHashList": [
          706872250985,
          684658785976,
          798670087502,
          489404563107
        ]
      },
      {
        "$type": "MoleMole.Config.ConfigDialogInterAction",
        "type": "DIALOG",
        "aliasList": [
          "1006"
        ],
        "dialogID": 3930107,
        "protectTime": 1.8083327
      },
      {
        "$type": "MoleMole.Config.ConfigBodyLangInterAction",
        "type": "BODY_LANG",
        "aliasList": [
          "1006"
        ],
        "bodyLangParam": 1170
      },
      {
        "$type": "MoleMole.Config.ConfigBodyLangInterAction",
        "type": "BODY_LANG",
        "delayTime": 1.7083327,
        "aliasList": [
          "1006"
        ],
        "isContinue": true
      },
      {
        "$type": "MoleMole.Config.ConfigEmoSyncInterAction",
        "type": "EMO_SYNC",
        "aliasList": [
          "1006"
        ],
        "dataPath": "Cs_Emo_Avatar_Simple_Common_Set/Cs_Emo_Avatar_Talk/Cs_Emo_Avatar_MainLine/Cs_Emo_Avatar_MengDe/Cs_Emo_3930107",
        "phonemePath": "",
        "emotionPath": "",
        "mateDataPath": "",
        "matePhonemePath": "",
        "mateEmotionPath": "",
        "dataPathHashList": [
          277871438544,
          126965488920,
          85828433615,
          227726721312
        ]
      }
    ],
    [
      {
        "$type": "MoleMole.Config.ConfigCameraMoveInterAction",
        "type": "CAMERA_MOVE",
        "duration": 1.0,
        "camPosOffset": {
          "x": 2659.4507,
          "y": 302.55743,
          "z": 115.73249
        },
        "camForwardTargetOffset": {
          "x": 2659.2515,
          "y": 302.32306,
          "z": 116.684
        },
        "camFov": 25.0,
        "lerpPattern": 6,
        "cameraBlendType": "EaseInOutCubic",
        "cutFrameTrans": {},
        "targetNpcAlias": ""
      },
      {
        "$type": "MoleMole.Config.ConfigCameraMoveInterAction",
        "type": "CAMERA_MOVE",
        "delayTime": 0.1,
        "duration": 10.0,
        "camPosOffset": {
          "x": 2659.7065,
          "y": 302.5858,
          "z": 115.79997
        },
        "camForwardTargetOffset": {
          "x": 2659.4707,
          "y": 302.34558,
          "z": 116.74161
        },
        "camFov": 25.0,
        "cameraBlendType": "EaseInOutQuad",
        "cutFrameTrans": {},
        "targetNpcAlias": ""
      },
      {
        "$type": "MoleMole.Config.ConfigCameraDOFAction",
        "type": "CAMERA_DOF",
        "enabled": true,
        "focusDistance": 5.0,
        "focusRange": 8.0,
        "quality": 3
      },
      {
        "$type": "MoleMole.Config.ConfigLookAtInterAction",
        "type": "LOOK_AT",
        "delayTime": 0.34293583,
        "aliasList": [
          "Avatar"
        ],
        "enableHead": true,
        "useTargetPos": true,
        "enableAbsolute": true,
        "targetPosition": {
          "x": 2658.9949,
          "y": 302.30194,
          "z": 118.28852
        },
        "headTurnTime": 0.3,
        "targetNpcAlias": ""
      },
      {
        "$type": "MoleMole.Config.ConfigLookAtInterAction",
        "type": "LOOK_AT",
        "delayTime": 0.48010993,
        "aliasList": [
          "1001"
        ],
        "enableHead": true,
        "useTargetPos": true,
        "enableAbsolute": true,
        "targetPosition": {
          "x": 2658.9949,
          "y": 302.30194,
          "z": 118.28852
        },
        "headTurnTime": 0.4,
        "targetNpcAlias": ""
      },
      {
        "$type": "MoleMole.Config.ConfigLookAtInterAction",
        "type": "LOOK_AT",
        "delayTime": 0.4234943,
        "aliasList": [
          "1009"
        ],
        "enableHead": true,
        "useTargetPos": true,
        "enableAbsolute": true,
        "targetPosition": {
          "x": 2659.1162,
          "y": 301.94095,
          "z": 120.64831
        },
        "headTurnTime": 0.3,
        "targetNpcAlias": ""
      },
      {
        "$type": "MoleMole.Config.ConfigLookAtInterAction",
        "type": "LOOK_AT",
        "delayTime": 0.605853,
        "aliasList": [
          "1006"
        ],
        "enableHead": true,
        "useTargetPos": true,
        "enableAbsolute": true,
        "targetPosition": {
          "x": 2658.9949,
          "y": 302.30194,
          "z": 118.28852
        },
        "headTurnTime": 0.3,
        "targetNpcAlias": ""
      },
      {
        "$type": "MoleMole.Config.ConfigDialogInterAction",
        "type": "DIALOG",
        "aliasList": [
          "1005"
        ],
        "dialogID": 3930110,
        "protectTime": 0.9001829
      },
      {
        "$type": "MoleMole.Config.ConfigLookAtInterAction",
        "type": "LOOK_AT",
        "delayTime": 0.11431186,
        "aliasList": [
          "1005"
        ],
        "enableHead": true,
        "useTargetPos": true,
        "enableAbsolute": true,
        "targetPosition": {
          "x": 2658.9949,
          "y": 302.30194,
          "z": 118.28852
        },
        "headTurnTime": 0.25,
        "targetNpcAlias": ""
      },
      {
        "$type": "MoleMole.Config.ConfigSteerInterAction",
        "type": "STEER_TO",
        "duration": 1.0,
        "aliasList": [
          "1005"
        ],
        "steerDir": {
          "x": -0.12993637,
          "z": -0.9915223
        },
        "targetNpcAlias": ""
      },
      {
        "$type": "MoleMole.Config.ConfigBodyLangInterAction",
        "type": "BODY_LANG",
        "delayTime": 0.8001829,
        "aliasList": [
          "1005"
        ],
        "bodyLangParam": 1170
      },
      {
        "$type": "MoleMole.Config.ConfigEmoSyncInterAction",
        "type": "EMO_SYNC",
        "aliasList": [
          "1005"
        ],
        "dataPath": "Cs_Emo_Avatar_Simple_Common_Set/Cs_Emo_Avatar_Talk/Cs_Emo_Avatar_MainLine/Cs_Emo_Avatar_MengDe/Cs_Emo_3930110",
        "phonemePath": "",
        "emotionPath": "",
        "mateDataPath": "",
        "matePhonemePath": "",
        "mateEmotionPath": "",
        "dataPathHashList": [
          821190465298,
          633212304827,
          301277980324,
          130352165862
        ]
      }
    ],
    [
      {
        "$type": "MoleMole.Config.ConfigCameraMoveInterAction",
        "type": "CAMERA_MOVE",
        "duration": 1.0,
        "camPosOffset": {
          "x": 2659.2017,
          "y": 302.0919,
          "z": 118.632095
        },
        "camForwardTargetOffset": {
          "x": 2659.1726,
          "y": 301.9192,
          "z": 119.616646
        },
        "camFov": 25.0,
        "lerpPattern": 6,
        "cameraBlendType": "EaseInOutCubic",
        "cutFrameTrans": {},
        "targetNpcAlias": ""
      },
      {
        "$type": "MoleMole.Config.ConfigCameraDOFAction",
        "type": "CAMERA_DOF",
        "enabled": true,
        "focusDistance": 2.0,
        "focusRange": 3.0,
        "quality": 3
      },
      {
        "$type": "MoleMole.Config.ConfigDialogInterAction",
        "type": "DIALOG",
        "aliasList": [
          "1005"
        ],
        "dialogID": 3930111
      },
      {
        "$type": "MoleMole.Config.ConfigEmoSyncInterAction",
        "type": "EMO_SYNC",
        "aliasList": [
          "1005"
        ],
        "dataPath": "Cs_Emo_Avatar_Simple_Common_Set/Cs_Emo_Avatar_Talk/Cs_Emo_Avatar_MainLine/Cs_Emo_Avatar_MengDe/Cs_Emo_3930111",
        "phonemePath": "",
        "emotionPath": "",
        "mateDataPath": "",
        "matePhonemePath": "",
        "mateEmotionPath": "",
        "dataPathHashList": [
          417600676374,
          987318969468,
          864611575667,
          739375388222
        ]
      }
    ],
    [
      {
        "$type": "MoleMole.Config.ConfigDialogInterAction",
        "type": "DIALOG",
        "aliasList": [
          "1005"
        ],
        "dialogID": 3930112
      },
      {
        "$type": "MoleMole.Config.ConfigBodyLangInterAction",
        "type": "BODY_LANG",
        "aliasList": [
          "1005"
        ],
        "bodyLangParam": 1110
      },
      {
        "$type": "MoleMole.Config.ConfigEmoSyncInterAction",
        "type": "EMO_SYNC",
        "aliasList": [
          "1005"
        ],
        "dataPath": "Cs_Emo_Avatar_Simple_Common_Set/Cs_Emo_Avatar_Talk/Cs_Emo_Avatar_MainLine/Cs_Emo_Avatar_MengDe/Cs_Emo_3930112",
        "phonemePath": "",
        "emotionPath": "",
        "mateDataPath": "",
        "matePhonemePath": "",
        "mateEmotionPath": "",
        "dataPathHashList": [
          250405337872,
          685991360484,
          1029390923242,
          314978228499
        ]
      }
    ],
    [
      {
        "$type": "MoleMole.Config.ConfigCameraMoveInterAction",
        "type": "CAMERA_MOVE",
        "duration": 1.0,
        "camPosOffset": {
          "x": 2660.7996,
          "y": 302.23172,
          "z": 123.520226
        },
        "camForwardTargetOffset": {
          "x": 2660.3118,
          "y": 302.0827,
          "z": 122.660095
        },
        "camFov": 25.0,
        "lerpPattern": 6,
        "cameraBlendType": "EaseInOutCubic",
        "cutFrameTrans": {},
        "targetNpcAlias": ""
      },
      {
        "$type": "MoleMole.Config.ConfigCameraMoveInterAction",
        "type": "CAMERA_MOVE",
        "delayTime": 0.1,
        "duration": 10.0,
        "camPosOffset": {
          "x": 2660.4219,
          "y": 302.13388,
          "z": 123.651054
        },
        "camForwardTargetOffset": {
          "x": 2660.037,
          "y": 301.99673,
          "z": 122.73828
        },
        "camFov": 25.0,
        "cameraBlendType": "EaseInOutQuad",
        "cutFrameTrans": {},
        "targetNpcAlias": ""
      },
      {
        "$type": "MoleMole.Config.ConfigCameraDOFAction",
        "type": "CAMERA_DOF",
        "enabled": true,
        "focusDistance": 5.0,
        "focusRange": 8.0,
        "quality": 3
      },
      {
        "$type": "MoleMole.Config.ConfigDialogSelectAction",
        "type": "DIALOG_SELECT",
        "delayTime": 1.0,
        "aliasList": [
          "Avatar"
        ],
        "dialogIDList": [
          3930114,
          3930117,
          3930120
        ],
        "grpIDList": [
          3544466986,
          3544466988,
          3544466990
        ],
        "useGrpId": true
      },
      {
        "$type": "MoleMole.Config.ConfigDialogInterAction",
        "type": "DIALOG",
        "aliasList": [
          "1009"
        ],
        "dialogID": 3930113,
        "protectTime": 0.2
      },
      {
        "$type": "MoleMole.Config.ConfigEmoSyncInterAction",
        "type": "EMO_SYNC",
        "aliasList": [
          "1009"
        ],
        "dataPath": "Cs_Emo_Avatar_Simple_Common_Set/Cs_Emo_Avatar_Talk/Cs_Emo_Avatar_MainLine/Cs_Emo_Avatar_MengDe/Cs_Emo_3930113",
        "phonemePath": "",
        "emotionPath": "",
        "mateDataPath": "",
        "matePhonemePath": "",
        "mateEmotionPath": "",
        "dataPathHashList": [
          544052495872,
          133473226706,
          354203689634,
          103324921908
        ]
      },
      {
        "$type": "MoleMole.Config.ConfigBodyLangInterAction",
        "type": "BODY_LANG",
        "aliasList": [
          "1005"
        ],
        "isContinue": true
      },
      {
        "$type": "MoleMole.Config.ConfigEmoSyncInterAction",
        "type": "EMO_SYNC",
        "aliasList": [
          "1005"
        ],
        "dataPath": "Cs_Emo_Avatar_Simple_Common_Set/Cs_Emo_Avatar_Paimon/Cs_Emo_Pet_Paimon_Normal_01",
        "phonemePath": "",
        "emotionPath": "",
        "mateDataPath": "",
        "matePhonemePath": "",
        "mateEmotionPath": "",
        "dataPathHashList": [
          770275607368,
          889535576943,
          237688024720,
          533776223999
        ]
      }
    ],
    [
      {
        "$type": "MoleMole.Config.ConfigCameraMoveInterAction",
        "type": "CAMERA_MOVE",
        "duration": 1.0,
        "camPosOffset": {
          "x": 2661.6174,
          "y": 302.10666,
          "z": 122.60457
        },
        "camForwardTargetOffset": {
          "x": 2660.7822,
          "y": 302.03217,
          "z": 122.05981
        },
        "camFov": 15.0,
        "lerpPattern": 6,
        "cameraBlendType": "EaseInOutCubic",
        "cutFrameTrans": {},
        "targetNpcAlias": ""
      },
      {
        "$type": "MoleMole.Config.ConfigLookAtInterAction",
        "type": "LOOK_AT",
        "delayTime": 0.45724747,
        "aliasList": [
          "Avatar"
        ],
        "enableHead": true,
        "useTargetPos": true,
        "enableAbsolute": true,
        "targetPosition": {
          "x": 2657.6443,
          "y": 302.1969,
          "z": 120.384705
        },
        "headTurnTime": 0.3,
        "targetNpcAlias": ""
      },
      {
        "$type": "MoleMole.Config.ConfigLookAtInterAction",
        "type": "LOOK_AT",
        "delayTime": 0.5893826,
        "aliasList": [
          "1001"
        ],
        "enableHead": true,
        "useTargetPos": true,
        "enableAbsolute": true,
        "targetPosition": {
          "x": 2659.1162,
          "y": 301.94095,
          "z": 120.64831
        },
        "headTurnTime": 0.3,
        "targetNpcAlias": ""
      },
      {
        "$type": "MoleMole.Config.ConfigLookAtInterAction",
        "type": "LOOK_AT",
        "delayTime": 0.5779515,
        "aliasList": [
          "1006"
        ],
        "enableHead": true,
        "useTargetPos": true,
        "enableAbsolute": true,
        "targetPosition": {
          "x": 2659.1162,
          "y": 301.94095,
          "z": 120.64831
        },
        "headTurnTime": 0.3,
        "targetNpcAlias": ""
      },
      {
        "$type": "MoleMole.Config.ConfigDialogInterAction",
        "type": "DIALOG",
        "aliasList": [
          "1005"
        ],
        "dialogID": 3930115,
        "protectTime": 2.2440217
      },
      {
        "$type": "MoleMole.Config.ConfigLookAtInterAction",
        "type": "LOOK_AT",
        "delayTime": 0.12574305,
        "aliasList": [
          "1005"
        ],
        "enableHead": true,
        "useTargetPos": true,
        "enableAbsolute": true,
        "targetPosition": {
          "x": 2657.6443,
          "y": 302.1969,
          "z": 120.384705
        },
        "headTurnTime": 0.25,
        "targetNpcAlias": ""
      },
      {
        "$type": "MoleMole.Config.ConfigSteerInterAction",
        "type": "STEER_TO",
        "duration": 1.0,
        "aliasList": [
          "1005"
        ],
        "steerDir": {
          "x": -0.92203903,
          "z": -0.3870969
        },
        "targetNpcAlias": ""
      },
      {
        "$type": "MoleMole.Config.ConfigBodyLangInterAction",
        "type": "BODY_LANG",
        "delayTime": 0.6287151,
        "aliasList": [
          "1005"
        ],
        "bodyLangParam": 1180
      },
      {
        "$type": "MoleMole.Config.ConfigBodyLangInterAction",
        "type": "BODY_LANG",
        "delayTime": 2.1440217,
        "aliasList": [
          "1005"
        ],
        "isContinue": true
      }
    ],
    [
      {
        "$type": "MoleMole.Config.ConfigCameraMoveInterAction",
        "type": "CAMERA_MOVE",
        "duration": 1.0,
        "camPosOffset": {
          "x": 2661.9976,
          "y": 302.03452,
          "z": 121.90597
        },
        "camForwardTargetOffset": {
          "x": 2661.1482,
          "y": 301.9361,
          "z": 121.387596
        },
        "camFov": 20.0,
        "cameraBlendType": "EaseInOutQuad",
        "cutFrameTrans": {},
        "targetNpcAlias": ""
      },
      {
        "$type": "MoleMole.Config.ConfigLookAtInterAction",
        "type": "LOOK_AT",
        "delayTime": 0.6058528,
        "aliasList": [
          "Avatar"
        ],
        "enableHead": true,
        "useTargetPos": true,
        "enableAbsolute": true,
        "targetPosition": {
          "x": 2657.7314,
          "y": 302.1162,
          "z": 119.14318
        },
        "headTurnTime": 0.3,
        "targetNpcAlias": ""
      },
      {
        "$type": "MoleMole.Config.ConfigLookAtInterAction",
        "type": "LOOK_AT",
        "delayTime": 0.34293556,
        "aliasList": [
          "1009"
        ],
        "enableHead": true,
        "headRotateVec": {
          "x": 346.48395,
          "y": 13.130137
        },
        "headTurnTime": 0.3,
        "targetNpcAlias": ""
      },
      {
        "$type": "MoleMole.Config.ConfigLookAtInterAction",
        "type": "LOOK_AT",
        "delayTime": 0.5144033,
        "aliasList": [
          "1006"
        ],
        "enableHead": true,
        "useTargetPos": true,
        "enableAbsolute": true,
        "targetPosition": {
          "x": 2657.7314,
          "y": 302.1162,
          "z": 119.14318
        },
        "headTurnTime": 0.3,
        "targetNpcAlias": ""
      },
      {
        "$type": "MoleMole.Config.ConfigDialogInterAction",
        "type": "DIALOG",
        "aliasList": [
          "1005"
        ],
        "dialogID": 3930116,
        "protectTime": 0.7058528
      },
      {
        "$type": "MoleMole.Config.ConfigLookAtInterAction",
        "type": "LOOK_AT",
        "delayTime": 0.12574305,
        "aliasList": [
          "1005"
        ],
        "enableHead": true,
        "useTargetPos": true,
        "enableAbsolute": true,
        "targetPosition": {
          "x": 2657.7314,
          "y": 302.1162,
          "z": 119.14318
        },
        "headTurnTime": 0.25,
        "targetNpcAlias": ""
      },
      {
        "$type": "MoleMole.Config.ConfigSteerInterAction",
        "type": "STEER_TO",
        "duration": 1.0,
        "aliasList": [
          "1005"
        ],
        "steerDir": {
          "x": -0.7124719,
          "z": -0.7017006
        },
        "targetNpcAlias": ""
      },
      {
        "$type": "MoleMole.Config.ConfigBodyLangInterAction",
        "type": "BODY_LANG",
        "delayTime": 0.55464125,
        "aliasList": [
          "1005"
        ],
        "bodyLangParam": 1090
      }
    ],
    [
      {
        "$type": "MoleMole.Config.ConfigCameraMoveInterAction",
        "type": "CAMERA_MOVE",
        "duration": 1.0,
        "camPosOffset": {
          "x": 2657.4614,
          "y": 302.27838,
          "z": 116.86293
        },
        "camForwardTargetOffset": {
          "x": 2658.0789,
          "y": 302.12048,
          "z": 117.63352
        },
        "camFov": 25.0,
        "lerpPattern": 6,
        "cameraBlendType": "EaseInOutCubic",
        "cutFrameTrans": {},
        "targetNpcAlias": ""
      },
      {
        "$type": "MoleMole.Config.ConfigLookAtInterAction",
        "type": "LOOK_AT",
        "delayTime": 0.32007346,
        "aliasList": [
          "Avatar"
        ],
        "enableHead": true,
        "useTargetPos": true,
        "enableAbsolute": true,
        "targetPosition": {
          "x": 2658.9949,
          "y": 302.30194,
          "z": 118.28852
        },
        "headTurnTime": 0.4,
        "targetNpcAlias": ""
      },
      {
        "$type": "MoleMole.Config.ConfigLookAtInterAction",
        "type": "LOOK_AT",
        "delayTime": 0.48010993,
        "aliasList": [
          "1001"
        ],
        "enableHead": true,
        "useTargetPos": true,
        "enableAbsolute": true,
        "targetPosition": {
          "x": 2658.9949,
          "y": 302.30194,
          "z": 118.28852
        },
        "headTurnTime": 0.4,
        "targetNpcAlias": ""
      },
      {
        "$type": "MoleMole.Config.ConfigLookAtInterAction",
        "type": "LOOK_AT",
        "delayTime": 0.4343854,
        "aliasList": [
          "1006"
        ],
        "enableHead": true,
        "useTargetPos": true,
        "enableAbsolute": true,
        "targetPosition": {
          "x": 2658.9949,
          "y": 302.30194,
          "z": 118.28852
        },
        "headTurnTime": 0.3,
        "targetNpcAlias": ""
      },
      {
        "$type": "MoleMole.Config.ConfigDialogInterAction",
        "type": "DIALOG",
        "aliasList": [
          "1005"
        ],
        "dialogID": 3930118,
        "protectTime": 1.6381687
      },
      {
        "$type": "MoleMole.Config.ConfigBodyLangInterAction",
        "type": "BODY_LANG",
        "aliasList": [
          "1005"
        ],
        "bodyLangParam": 1180
      },
      {
        "$type": "MoleMole.Config.ConfigBodyLangInterAction",
        "type": "BODY_LANG",
        "delayTime": 1.5381687,
        "aliasList": [
          "1005"
        ],
        "isContinue": true
      },
      {
        "$type": "MoleMole.Config.ConfigLookAtInterAction",
        "type": "LOOK_AT",
        "aliasList": [
          "1005"
        ],
        "enableHead": true,
        "useTargetPos": true,
        "enableAbsolute": true,
        "targetPosition": {
          "x": 2658.9949,
          "y": 302.30194,
          "z": 118.28852
        },
        "headTurnTime": 0.3,
        "targetNpcAlias": ""
      },
      {
        "$type": "MoleMole.Config.ConfigEmoSyncInterAction",
        "type": "EMO_SYNC",
        "aliasList": [
          "1005"
        ],
        "dataPath": "Cs_Emo_Avatar_Simple_Common_Set/Cs_Emo_Avatar_Talk/Cs_Emo_Avatar_MainLine/Cs_Emo_Avatar_MengDe/Cs_Emo_3930118",
        "phonemePath": "",
        "emotionPath": "",
        "mateDataPath": "",
        "matePhonemePath": "",
        "mateEmotionPath": "",
        "dataPathHashList": [
          766843407403,
          151956616176,
          789867633854,
          282615308997
        ]
      }
    ],
    [
      {
        "$type": "MoleMole.Config.ConfigCameraMoveInterAction",
        "type": "CAMERA_MOVE",
        "duration": 1.0,
        "camPosOffset": {
          "x": 2656.9456,
          "y": 302.06952,
          "z": 117.01196
        },
        "camForwardTargetOffset": {
          "x": 2657.401,
          "y": 301.93536,
          "z": 117.892075
        },
        "camFov": 25.0,
        "cameraBlendType": "EaseInOutQuad",
        "cutFrameTrans": {},
        "targetNpcAlias": ""
      },
      {
        "$type": "MoleMole.Config.ConfigLookAtInterAction",
        "type": "LOOK_AT",
        "delayTime": 0.6058528,
        "aliasList": [
          "Avatar"
        ],
        "enableHead": true,
        "useTargetPos": true,
        "enableAbsolute": true,
        "targetPosition": {
          "x": 2657.7314,
          "y": 302.1162,
          "z": 119.14318
        },
        "headTurnTime": 0.3,
        "targetNpcAlias": ""
      },
      {
        "$type": "MoleMole.Config.ConfigLookAtInterAction",
        "type": "LOOK_AT",
        "delayTime": 0.5893826,
        "aliasList": [
          "1001"
        ],
        "enableHead": true,
        "useTargetPos": true,
        "enableAbsolute": true,
        "targetPosition": {
          "x": 2659.1162,
          "y": 301.94095,
          "z": 120.64831
        },
        "headTurnTime": 0.3,
        "targetNpcAlias": ""
      },
      {
        "$type": "MoleMole.Config.ConfigLookAtInterAction",
        "type": "LOOK_AT",
        "delayTime": 0.34293556,
        "aliasList": [
          "1009"
        ],
        "enableHead": true,
        "headRotateVec": {
          "x": 346.48395,
          "y": 13.130137
        },
        "headTurnTime": 0.3,
        "targetNpcAlias": ""
      },
      {
        "$type": "MoleMole.Config.ConfigLookAtInterAction",
        "type": "LOOK_AT",
        "delayTime": 0.5144033,
        "aliasList": [
          "1006"
        ],
        "enableHead": true,
        "useTargetPos": true,
        "enableAbsolute": true,
        "targetPosition": {
          "x": 2657.7314,
          "y": 302.1162,
          "z": 119.14318
        },
        "headTurnTime": 0.3,
        "targetNpcAlias": ""
      },
      {
        "$type": "MoleMole.Config.ConfigDialogInterAction",
        "type": "DIALOG",
        "aliasList": [
          "1005"
        ],
        "dialogID": 3930119,
        "protectTime": 0.80324656
      },
      {
        "$type": "MoleMole.Config.ConfigSteerInterAction",
        "type": "STEER_TO",
        "duration": 1.0,
        "aliasList": [
          "1005"
        ],
        "steerDir": {
          "x": -0.7124719,
          "z": -0.7017006
        },
        "targetNpcAlias": ""
      },
      {
        "$type": "MoleMole.Config.ConfigLookAtInterAction",
        "type": "LOOK_AT",
        "delayTime": 0.12574305,
        "aliasList": [
          "1005"
        ],
        "enableHead": true,
        "useTargetPos": true,
        "enableAbsolute": true,
        "targetPosition": {
          "x": 2657.7314,
          "y": 302.1162,
          "z": 119.14318
        },
        "headTurnTime": 0.25,
        "targetNpcAlias": ""
      },
      {
        "$type": "MoleMole.Config.ConfigBodyLangInterAction",
        "type": "BODY_LANG",
        "delayTime": 0.70324653,
        "aliasList": [
          "1005"
        ],
        "bodyLangParam": 1090
      },
      {
        "$type": "MoleMole.Config.ConfigEmoSyncInterAction",
        "type": "EMO_SYNC",
        "aliasList": [
          "1005"
        ],
        "dataPath": "Cs_Emo_Avatar_Simple_Common_Set/Cs_Emo_Avatar_Talk/Cs_Emo_Avatar_MainLine/Cs_Emo_Avatar_MengDe/Cs_Emo_3930119",
        "phonemePath": "",
        "emotionPath": "",
        "mateDataPath": "",
        "matePhonemePath": "",
        "mateEmotionPath": "",
        "dataPathHashList": [
          1067135437853,
          2305415960,
          892008746425,
          918492165977
        ]
      }
    ],
    [
      {
        "$type": "MoleMole.Config.ConfigCameraMoveInterAction",
        "type": "CAMERA_MOVE",
        "duration": 1.0,
        "camPosOffset": {
          "x": 2659.159,
          "y": 301.8715,
          "z": 120.24968
        },
        "camForwardTargetOffset": {
          "x": 2658.348,
          "y": 301.80597,
          "z": 119.66849
        },
        "camFov": 30.0,
        "lerpPattern": 6,
        "cameraBlendType": "EaseInOutCubic",
        "cutFrameTrans": {},
        "targetNpcAlias": ""
      },
      {
        "$type": "MoleMole.Config.ConfigCameraDOFAction",
        "type": "CAMERA_DOF",
        "enabled": true,
        "focusDistance": 2.0,
        "focusRange": 3.0,
        "quality": 3
      },
      {
        "$type": "MoleMole.Config.ConfigLookAtInterAction",
        "type": "LOOK_AT",
        "delayTime": 0.6058528,
        "aliasList": [
          "Avatar"
        ],
        "enableHead": true,
        "useTargetPos": true,
        "enableAbsolute": true,
        "targetPosition": {
          "x": 2657.7314,
          "y": 302.1162,
          "z": 119.14318
        },
        "headTurnTime": 0.3,
        "targetNpcAlias": ""
      },
      {
        "$type": "MoleMole.Config.ConfigDialogInterAction",
        "type": "DIALOG",
        "aliasList": [
          "1001"
        ],
        "dialogID": 3930121,
        "protectTime": 2.0319638
      },
      {
        "$type": "MoleMole.Config.ConfigBodyLangInterAction",
        "type": "BODY_LANG",
        "aliasList": [
          "1001"
        ],
        "bodyLangParam": 1110
      },
      {
        "$type": "MoleMole.Config.ConfigBodyLangInterAction",
        "type": "BODY_LANG",
        "delayTime": 1.9319638,
        "aliasList": [
          "1001"
        ],
        "isContinue": true
      },
      {
        "$type": "MoleMole.Config.ConfigEmoSyncInterAction",
        "type": "EMO_SYNC",
        "aliasList": [
          "1001"
        ],
        "dataPath": "Cs_Emo_Avatar_Simple_Common_Set/Cs_Emo_Avatar_Talk/Cs_Emo_Avatar_MainLine/Cs_Emo_Avatar_MengDe/Cs_Emo_3930121",
        "phonemePath": "",
        "emotionPath": "",
        "mateDataPath": "",
        "matePhonemePath": "",
        "mateEmotionPath": "",
        "dataPathHashList": [
          888335417022,
          955552641569,
          915711089095,
          237094611993
        ]
      },
      {
        "$type": "MoleMole.Config.ConfigLookAtInterAction",
        "type": "LOOK_AT",
        "delayTime": 0.34293556,
        "aliasList": [
          "1009"
        ],
        "enableHead": true,
        "headRotateVec": {
          "x": 346.48395,
          "y": 13.130137
        },
        "headTurnTime": 0.3,
        "targetNpcAlias": ""
      },
      {
        "$type": "MoleMole.Config.ConfigLookAtInterAction",
        "type": "LOOK_AT",
        "delayTime": 0.5144033,
        "aliasList": [
          "1006"
        ],
        "enableHead": true,
        "useTargetPos": true,
        "enableAbsolute": true,
        "targetPosition": {
          "x": 2657.7314,
          "y": 302.1162,
          "z": 119.14318
        },
        "headTurnTime": 0.3,
        "targetNpcAlias": ""
      },
      {
        "$type": "MoleMole.Config.ConfigBodyLangInterAction",
        "type": "BODY_LANG",
        "delayTime": 1.1568521,
        "aliasList": [
          "1005"
        ],
        "isContinue": true
      },
      {
        "$type": "MoleMole.Config.ConfigLookAtInterAction",
        "type": "LOOK_AT",
        "delayTime": 0.12574305,
        "aliasList": [
          "1005"
        ],
        "enableHead": true,
        "useTargetPos": true,
        "enableAbsolute": true,
        "targetPosition": {
          "x": 2657.7314,
          "y": 302.1162,
          "z": 119.14318
        },
        "headTurnTime": 0.25,
        "targetNpcAlias": ""
      },
      {
        "$type": "MoleMole.Config.ConfigSteerInterAction",
        "type": "STEER_TO",
        "duration": 1.0,
        "aliasList": [
          "1005"
        ],
        "steerDir": {
          "x": -0.7124719,
          "z": -0.7017006
        },
        "targetNpcAlias": ""
      }
    ],
    [
      {
        "$type": "MoleMole.Config.ConfigCameraMoveInterAction",
        "type": "CAMERA_MOVE",
        "duration": 1.0,
        "camPosOffset": {
          "x": 2656.932,
          "y": 302.3938,
          "z": 117.02806
        },
        "camForwardTargetOffset": {
          "x": 2657.3428,
          "y": 302.19458,
          "z": 117.91776
        },
        "camFov": 20.0,
        "lerpPattern": 6,
        "cameraBlendType": "EaseInOutCubic",
        "cutFrameTrans": {},
        "targetNpcAlias": ""
      },
      {
        "$type": "MoleMole.Config.ConfigCameraDOFAction",
        "type": "CAMERA_DOF",
        "enabled": true,
        "focusDistance": 5.0,
        "focusRange": 8.0,
        "quality": 3
      },
      {
        "$type": "MoleMole.Config.ConfigDialogInterAction",
        "type": "DIALOG",
        "aliasList": [
          "1005"
        ],
        "dialogID": 3930122,
        "protectTime": 0.1
      },
      {
        "$type": "MoleMole.Config.ConfigBodyLangInterAction",
        "type": "BODY_LANG",
        "aliasList": [
          "1005"
        ],
        "bodyLangParam": 1190
      },
      {
        "$type": "MoleMole.Config.ConfigEmoSyncInterAction",
        "type": "EMO_SYNC",
        "aliasList": [
          "1005"
        ],
        "dataPath": "Cs_Emo_Avatar_Simple_Common_Set/Cs_Emo_Avatar_Talk/Cs_Emo_Avatar_MainLine/Cs_Emo_Avatar_MengDe/Cs_Emo_3930122",
        "phonemePath": "",
        "emotionPath": "",
        "mateDataPath": "",
        "matePhonemePath": "",
        "mateEmotionPath": "",
        "dataPathHashList": [
          646617883994,
          491074292546,
          584775611979,
          893006540589
        ]
      }
    ],
    [
      {
        "$type": "MoleMole.Config.ConfigCameraMoveInterAction",
        "type": "CAMERA_MOVE",
        "duration": 1.0,
        "camPosOffset": {
          "x": 2660.6226,
          "y": 301.95853,
          "z": 124.1693
        },
        "camForwardTargetOffset": {
          "x": 2660.244,
          "y": 301.8452,
          "z": 123.250755
        },
        "camFov": 25.0,
        "lerpPattern": 6,
        "cameraBlendType": "EaseInOutCubic",
        "cutFrameTrans": {},
        "targetNpcAlias": ""
      },
      {
        "$type": "MoleMole.Config.ConfigCameraMoveInterAction",
        "type": "CAMERA_MOVE",
        "delayTime": 0.1,
        "duration": 8.0,
        "camPosOffset": {
          "x": 2660.235,
          "y": 301.94565,
          "z": 124.315475
        },
        "camForwardTargetOffset": {
          "x": 2659.9065,
          "y": 301.8353,
          "z": 123.37752
        },
        "camFov": 25.0,
        "cameraBlendType": "EaseInOutQuad",
        "cutFrameTrans": {},
        "targetNpcAlias": ""
      },
      {
        "$type": "MoleMole.Config.ConfigCameraDOFAction",
        "type": "CAMERA_DOF",
        "enabled": true,
        "focusDistance": 8.0,
        "focusRange": 8.0,
        "quality": 3
      },
      {
        "$type": "MoleMole.Config.ConfigDialogSelectAction",
        "type": "DIALOG_SELECT",
        "delayTime": 1.0,
        "aliasList": [
          "Avatar"
        ],
        "dialogIDList": [
          3930124
        ],
        "grpIDList": [
          3544466993
        ],
        "useGrpId": true
      },
      {
        "$type": "MoleMole.Config.ConfigDialogInterAction",
        "type": "DIALOG",
        "aliasList": [
          "1001"
        ],
        "dialogID": 3930123,
        "protectTime": 2.026511
      },
      {
        "$type": "MoleMole.Config.ConfigBodyLangInterAction",
        "type": "BODY_LANG",
        "aliasList": [
          "1001"
        ],
        "bodyLangParam": 1170
      },
      {
        "$type": "MoleMole.Config.ConfigBodyLangInterAction",
        "type": "BODY_LANG",
        "delayTime": 1.9265109,
        "aliasList": [
          "1001"
        ],
        "isContinue": true
      },
      {
        "$type": "MoleMole.Config.ConfigEmoSyncInterAction",
        "type": "EMO_SYNC",
        "aliasList": [
          "1001"
        ],
        "dataPath": "Cs_Emo_Avatar_Simple_Common_Set/Cs_Emo_Avatar_Talk/Cs_Emo_Avatar_MainLine/Cs_Emo_Avatar_MengDe/Cs_Emo_3930123",
        "phonemePath": "",
        "emotionPath": "",
        "mateDataPath": "",
        "matePhonemePath": "",
        "mateEmotionPath": "",
        "dataPathHashList": [
          628109139018,
          729000474411,
          6742273543,
          22088629304
        ]
      },
      {
        "$type": "MoleMole.Config.ConfigLookAtInterAction",
        "type": "LOOK_AT",
        "delayTime": 0.8171179,
        "aliasList": [
          "1006"
        ],
        "enableHead": true,
        "useTargetPos": true,
        "enableAbsolute": true,
        "targetPosition": {
          "x": 2659.83,
          "y": 302.0415,
          "z": 119.84459
        },
        "headTurnTime": 0.3,
        "targetNpcAlias": ""
      },
      {
        "$type": "MoleMole.Config.ConfigBodyLangInterAction",
        "type": "BODY_LANG",
        "delayTime": 0.516378,
        "aliasList": [
          "1005"
        ],
        "isContinue": true
      }
    ],
    [
      {
        "$type": "MoleMole.Config.ConfigCameraMoveInterAction",
        "type": "CAMERA_MOVE",
        "duration": 1.0,
        "camPosOffset": {
          "x": 2659.41,
          "y": 301.93347,
          "z": 119.751526
        },
        "camForwardTargetOffset": {
          "x": 2658.4685,
          "y": 301.84702,
          "z": 119.425186
        },
        "camFov": 30.0,
        "lerpPattern": 6,
        "cameraBlendType": "EaseInOutCubic",
        "cutFrameTrans": {},
        "targetNpcAlias": ""
      },
      {
        "$type": "MoleMole.Config.ConfigCameraDOFAction",
        "type": "CAMERA_DOF",
        "enabled": true,
        "focusDistance": 2.0,
        "focusRange": 3.0,
        "quality": 3
      },
      {
        "$type": "MoleMole.Config.ConfigDialogInterAction",
        "type": "DIALOG",
        "aliasList": [
          "1001"
        ],
        "dialogID": 3930125,
        "protectTime": 1.9225141
      },
      {
        "$type": "MoleMole.Config.ConfigBodyLangInterAction",
        "type": "BODY_LANG",
        "aliasList": [
          "1001"
        ],
        "bodyLangParam": 1110
      },
      {
        "$type": "MoleMole.Config.ConfigBodyLangInterAction",
        "type": "BODY_LANG",
        "delayTime": 1.822514,
        "aliasList": [
          "1001"
        ],
        "isContinue": true
      },
      {
        "$type": "MoleMole.Config.ConfigLookAtInterAction",
        "type": "LOOK_AT",
        "aliasList": [
          "1001"
        ],
        "enableHead": true,
        "useTargetPos": true,
        "enableAbsolute": true,
        "targetPosition": {
          "x": 2659.83,
          "y": 302.0415,
          "z": 119.84459
        },
        "headTurnTime": 0.3,
        "targetNpcAlias": ""
      },
      {
        "$type": "MoleMole.Config.ConfigEmoSyncInterAction",
        "type": "EMO_SYNC",
        "aliasList": [
          "1001"
        ],
        "dataPath": "Cs_Emo_Avatar_Simple_Common_Set/Cs_Emo_Avatar_Talk/Cs_Emo_Avatar_MainLine/Cs_Emo_Avatar_MengDe/Cs_Emo_3930125",
        "phonemePath": "",
        "emotionPath": "",
        "mateDataPath": "",
        "matePhonemePath": "",
        "mateEmotionPath": "",
        "dataPathHashList": [
          1073212608121,
          259578357550,
          825612190859,
          961684994314
        ]
      },
      {
        "$type": "MoleMole.Config.ConfigLookAtInterAction",
        "type": "LOOK_AT",
        "delayTime": 0.6273039,
        "aliasList": [
          "1006"
        ],
        "enableHead": true,
        "useTargetPos": true,
        "enableAbsolute": true,
        "targetPosition": {
          "x": 2657.7314,
          "y": 302.1162,
          "z": 119.14318
        },
        "headTurnTime": 0.3,
        "targetNpcAlias": ""
      }
    ],
    [
      {
        "$type": "MoleMole.Config.ConfigDialogInterAction",
        "type": "DIALOG",
        "aliasList": [
          "1001"
        ],
        "dialogID": 3930126
      },
      {
        "$type": "MoleMole.Config.ConfigEmoSyncInterAction",
        "type": "EMO_SYNC",
        "aliasList": [
          "1001"
        ],
        "dataPath": "Cs_Emo_Avatar_Simple_Common_Set/Cs_Emo_Avatar_Talk/Cs_Emo_Avatar_MainLine/Cs_Emo_Avatar_MengDe/Cs_Emo_3930126",
        "phonemePath": "",
        "emotionPath": "",
        "mateDataPath": "",
        "matePhonemePath": "",
        "mateEmotionPath": "",
        "enableBlink": false,
        "dataPathHashList": [
          406366745275,
          269423606162,
          982548309105,
          624057037685
        ]
      }
    ],
    [
      {
        "$type": "MoleMole.Config.ConfigDialogInterAction",
        "type": "DIALOG",
        "aliasList": [
          "1001"
        ],
        "dialogID": 3930127
      },
      {
        "$type": "MoleMole.Config.ConfigEmoSyncInterAction",
        "type": "EMO_SYNC",
        "aliasList": [
          "1001"
        ],
        "dataPath": "Cs_Emo_Avatar_Simple_Common_Set/Cs_Emo_Avatar_Talk/Cs_Emo_Avatar_MainLine/Cs_Emo_Avatar_MengDe/Cs_Emo_3930127",
        "phonemePath": "",
        "emotionPath": "",
        "mateDataPath": "",
        "matePhonemePath": "",
        "mateEmotionPath": "",
        "dataPathHashList": [
          879582315676,
          298558287403,
          976972398548,
          39075059119
        ]
      }
    ],
    [
      {
        "$type": "MoleMole.Config.ConfigCameraMoveInterAction",
        "type": "CAMERA_MOVE",
        "duration": 1.0,
        "camPosOffset": {
          "x": 2667.3257,
          "y": 302.29016,
          "z": 116.02154
        },
        "camForwardTargetOffset": {
          "x": 2666.4077,
          "y": 302.2007,
          "z": 116.407814
        },
        "camFov": 12.0,
        "lerpPattern": 6,
        "cameraBlendType": "EaseInOutCubic",
        "cutFrameTrans": {},
        "targetNpcAlias": ""
      },
      {
        "$type": "MoleMole.Config.ConfigCameraMoveInterAction",
        "type": "CAMERA_MOVE",
        "delayTime": 0.1,
        "duration": 15.0,
        "camPosOffset": {
          "x": 2666.8147,
          "y": 302.375,
          "z": 115.732544
        },
        "camForwardTargetOffset": {
          "x": 2665.9104,
          "y": 302.27957,
          "z": 116.148674
        },
        "camFov": 12.0,
        "cameraBlendType": "EaseInOutQuad",
        "cutFrameTrans": {},
        "targetNpcAlias": ""
      },
      {
        "$type": "MoleMole.Config.ConfigCameraDOFAction",
        "type": "CAMERA_DOF",
        "enabled": true,
        "focusDistance": 10.0,
        "focusRange": 10.0,
        "quality": 3
      },
      {
        "$type": "MoleMole.Config.ConfigDialogInterAction",
        "type": "DIALOG",
        "aliasList": [
          "1001"
        ],
        "dialogID": 3930128
      },
      {
        "$type": "MoleMole.Config.ConfigBodyLangInterAction",
        "type": "BODY_LANG",
        "aliasList": [
          "1001"
        ],
        "bodyLangParam": 1180
      },
      {
        "$type": "MoleMole.Config.ConfigEmoSyncInterAction",
        "type": "EMO_SYNC",
        "aliasList": [
          "1001"
        ],
        "dataPath": "Cs_Emo_Avatar_Simple_Common_Set/Cs_Emo_Avatar_Talk/Cs_Emo_Avatar_MainLine/Cs_Emo_Avatar_MengDe/Cs_Emo_3930128",
        "phonemePath": "",
        "emotionPath": "",
        "mateDataPath": "",
        "matePhonemePath": "",
        "mateEmotionPath": "",
        "dataPathHashList": [
          5241831381,
          1020936272010,
          793141535731,
          432036668381
        ]
      }
    ],
    [
      {
        "$type": "MoleMole.Config.ConfigDialogInterAction",
        "type": "DIALOG",
        "aliasList": [
          "1001"
        ],
        "dialogID": 3930129
      },
      {
        "$type": "MoleMole.Config.ConfigEmoSyncInterAction",
        "type": "EMO_SYNC",
        "aliasList": [
          "1001"
        ],
        "dataPath": "Cs_Emo_Avatar_Simple_Common_Set/Cs_Emo_Avatar_Talk/Cs_Emo_Avatar_MainLine/Cs_Emo_Avatar_MengDe/Cs_Emo_3930129",
        "phonemePath": "",
        "emotionPath": "",
        "mateDataPath": "",
        "matePhonemePath": "",
        "mateEmotionPath": "",
        "dataPathHashList": [
          743538946102,
          228569813886,
          366398860564,
          267267092374
        ]
      }
    ],
    [
      {
        "$type": "MoleMole.Config.ConfigDialogInterAction",
        "type": "DIALOG",
        "aliasList": [
          "1001"
        ],
        "dialogID": 3930130
      },
      {
        "$type": "MoleMole.Config.ConfigEmoSyncInterAction",
        "type": "EMO_SYNC",
        "aliasList": [
          "1001"
        ],
        "dataPath": "Cs_Emo_Avatar_Simple_Common_Set/Cs_Emo_Avatar_Talk/Cs_Emo_Avatar_MainLine/Cs_Emo_Avatar_MengDe/Cs_Emo_3930130",
        "phonemePath": "",
        "emotionPath": "",
        "mateDataPath": "",
        "matePhonemePath": "",
        "mateEmotionPath": "",
        "dataPathHashList": [
          716708568678,
          825351948778,
          443249598335,
          362975345597
        ]
      }
    ],
    [
      {
        "$type": "MoleMole.Config.ConfigDialogInterAction",
        "type": "DIALOG",
        "aliasList": [
          "1001"
        ],
        "dialogID": 3930131,
        "protectTime": 0.8551126
      },
      {
        "$type": "MoleMole.Config.ConfigBodyLangInterAction",
        "type": "BODY_LANG",
        "delayTime": 0.7551126,
        "aliasList": [
          "1001"
        ],
        "isContinue": true
      },
      {
        "$type": "MoleMole.Config.ConfigEmoSyncInterAction",
        "type": "EMO_SYNC",
        "aliasList": [
          "1001"
        ],
        "dataPath": "Cs_Emo_Avatar_Simple_Common_Set/Cs_Emo_Avatar_Talk/Cs_Emo_Avatar_MainLine/Cs_Emo_Avatar_MengDe/Cs_Emo_3930131",
        "phonemePath": "",
        "emotionPath": "",
        "mateDataPath": "",
        "matePhonemePath": "",
        "mateEmotionPath": "",
        "dataPathHashList": [
          571462373297,
          50192738210,
          658579806253,
          732114659665
        ]
      }
    ],
    [
      {
        "$type": "MoleMole.Config.ConfigCameraMoveInterAction",
        "type": "CAMERA_MOVE",
        "duration": 1.0,
        "camPosOffset": {
          "x": 2658.049,
          "y": 301.90732,
          "z": 119.13844
        },
        "camForwardTargetOffset": {
          "x": 2658.6335,
          "y": 301.8119,
          "z": 119.94426
        },
        "camFov": 25.0,
        "lerpPattern": 6,
        "cameraBlendType": "EaseInOutCubic",
        "cutFrameTrans": {},
        "targetNpcAlias": ""
      },
      {
        "$type": "MoleMole.Config.ConfigCameraDOFAction",
        "type": "CAMERA_DOF",
        "enabled": true,
        "focusDistance": 2.0,
        "focusRange": 3.0,
        "quality": 3
      },
      {
        "$type": "MoleMole.Config.ConfigDialogInterAction",
        "type": "DIALOG",
        "aliasList": [
          "1005"
        ],
        "dialogID": 3930132
      },
      {
        "$type": "MoleMole.Config.ConfigBodyLangInterAction",
        "type": "BODY_LANG",
        "aliasList": [
          "1005"
        ],
        "bodyLangParam": 1130
      },
      {
        "$type": "MoleMole.Config.ConfigEmoSyncInterAction",
        "type": "EMO_SYNC",
        "aliasList": [
          "1005"
        ],
        "dataPath": "Cs_Emo_Avatar_Simple_Common_Set/Cs_Emo_Avatar_Talk/Cs_Emo_Avatar_MainLine/Cs_Emo_Avatar_MengDe/Cs_Emo_3930132",
        "phonemePath": "",
        "emotionPath": "",
        "mateDataPath": "",
        "matePhonemePath": "",
        "mateEmotionPath": "",
        "dataPathHashList": [
          183771247008,
          989689349626,
          626387017945,
          359507144241
        ]
      }
    ],
    [
      {
        "$type": "MoleMole.Config.ConfigCameraMoveInterAction",
        "type": "CAMERA_MOVE",
        "duration": 1.0,
        "camPosOffset": {
          "x": 2667.279,
          "y": 302.35254,
          "z": 115.9246
        },
        "camForwardTargetOffset": {
          "x": 2666.361,
          "y": 302.2631,
          "z": 116.310875
        },
        "camFov": 12.0,
        "lerpPattern": 6,
        "cameraBlendType": "EaseInOutCubic",
        "cutFrameTrans": {},
        "targetNpcAlias": ""
      },
      {
        "$type": "MoleMole.Config.ConfigCameraDOFAction",
        "type": "CAMERA_DOF",
        "enabled": true,
        "focusDistance": 10.0,
        "focusRange": 10.0,
        "quality": 3
      },
      {
        "$type": "MoleMole.Config.ConfigDialogInterAction",
        "type": "DIALOG",
        "aliasList": [
          "1001"
        ],
        "dialogID": 3930133,
        "protectTime": 1.1
      },
      {
        "$type": "MoleMole.Config.ConfigBodyLangInterAction",
        "type": "BODY_LANG",
        "delayTime": 1.0,
        "aliasList": [
          "1001"
        ],
        "bodyLangParam": 1130
      },
      {
        "$type": "MoleMole.Config.ConfigEmoSyncInterAction",
        "type": "EMO_SYNC",
        "aliasList": [
          "1001"
        ],
        "dataPath": "Cs_Emo_Avatar_Simple_Common_Set/Cs_Emo_Avatar_Talk/Cs_Emo_Avatar_MainLine/Cs_Emo_Avatar_MengDe/Cs_Emo_3930133",
        "phonemePath": "",
        "emotionPath": "",
        "mateDataPath": "",
        "matePhonemePath": "",
        "mateEmotionPath": "",
        "dataPathHashList": [
          391276682299,
          1037426410878,
          173772793893,
          96089098262
        ]
      },
      {
        "$type": "MoleMole.Config.ConfigLookAtInterAction",
        "type": "LOOK_AT",
        "delayTime": 0.3704551,
        "aliasList": [
          "1009"
        ],
        "enableHead": true,
        "useTargetPos": true,
        "enableAbsolute": true,
        "targetPosition": {
          "x": 2659.83,
          "y": 302.0415,
          "z": 119.84459
        },
        "headTurnTime": 0.3,
        "targetNpcAlias": ""
      },
      {
        "$type": "MoleMole.Config.ConfigLookAtInterAction",
        "type": "LOOK_AT",
        "delayTime": 0.9430728,
        "aliasList": [
          "1006"
        ],
        "enableHead": true,
        "useTargetPos": true,
        "enableAbsolute": true,
        "targetPosition": {
          "x": 2659.83,
          "y": 302.0415,
          "z": 119.84459
        },
        "headTurnTime": 0.3,
        "targetNpcAlias": ""
      },
      {
        "$type": "MoleMole.Config.ConfigBodyLangInterAction",
        "type": "BODY_LANG",
        "aliasList": [
          "1005"
        ],
        "isContinue": true
      },
      {
        "$type": "MoleMole.Config.ConfigEmoSyncInterAction",
        "type": "EMO_SYNC",
        "aliasList": [
          "1005"
        ],
        "dataPath": "Cs_Emo_Avatar_Simple_Common_Set/Cs_Emo_Avatar_Paimon/Cs_Emo_Pet_Paimon_Normal_01",
        "phonemePath": "",
        "emotionPath": "",
        "mateDataPath": "",
        "matePhonemePath": "",
        "mateEmotionPath": "",
        "dataPathHashList": [
          770275607368,
          889535576943,
          237688024720,
          533776223999
        ]
      }
    ],
    [
      {
        "$type": "MoleMole.Config.ConfigDialogSelectAction",
        "type": "DIALOG_SELECT",
        "delayTime": 0.8749997,
        "aliasList": [
          "Avatar"
        ],
        "dialogIDList": [
          3930135,
          3930136
        ],
        "grpIDList": [
          3544467024,
          3544467024
        ],
        "useGrpId": true
      },
      {
        "$type": "MoleMole.Config.ConfigDialogInterAction",
        "type": "DIALOG",
        "aliasList": [
          "1001"
        ],
        "dialogID": 3930134,
        "protectTime": 1.2134821
      },
      {
        "$type": "MoleMole.Config.ConfigBodyLangInterAction",
        "type": "BODY_LANG",
        "aliasList": [
          "1001"
        ],
        "isContinue": true
      },
      {
        "$type": "MoleMole.Config.ConfigEmoSyncInterAction",
        "type": "EMO_SYNC",
        "aliasList": [
          "1001"
        ],
        "dataPath": "Cs_Emo_Avatar_Simple_Common_Set/Cs_Emo_Avatar_Talk/Cs_Emo_Avatar_MainLine/Cs_Emo_Avatar_MengDe/Cs_Emo_3930134",
        "phonemePath": "",
        "emotionPath": "",
        "mateDataPath": "",
        "matePhonemePath": "",
        "mateEmotionPath": "",
        "dataPathHashList": [
          617948271942,
          44703155232,
          148800962691,
          722707761701
        ]
      }
    ],
    [
      {
        "$type": "MoleMole.Config.ConfigCameraMoveInterAction",
        "type": "CAMERA_MOVE",
        "duration": 1.0,
        "camPosOffset": {
          "x": 2658.049,
          "y": 301.90732,
          "z": 119.13844
        },
        "camForwardTargetOffset": {
          "x": 2658.6335,
          "y": 301.8119,
          "z": 119.94426
        },
        "camFov": 25.0,
        "lerpPattern": 6,
        "cameraBlendType": "EaseInOutCubic",
        "cutFrameTrans": {},
        "targetNpcAlias": ""
      },
      {
        "$type": "MoleMole.Config.ConfigCameraDOFAction",
        "type": "CAMERA_DOF",
        "enabled": true,
        "focusDistance": 2.0,
        "focusRange": 3.0,
        "quality": 3
      },
      {
        "$type": "MoleMole.Config.ConfigLookAtInterAction",
        "type": "LOOK_AT",
        "delayTime": 0.5081697,
        "aliasList": [
          "1009"
        ],
        "enableHead": true,
        "useTargetPos": true,
        "enableAbsolute": true,
        "targetPosition": {
          "x": 2659.1162,
          "y": 301.94095,
          "z": 120.64831
        },
        "headTurnTime": 0.3,
        "targetNpcAlias": ""
      },
      {
        "$type": "MoleMole.Config.ConfigLookAtInterAction",
        "type": "LOOK_AT",
        "delayTime": 0.5222823,
        "aliasList": [
          "1006"
        ],
        "enableHead": true,
        "useTargetPos": true,
        "enableAbsolute": true,
        "targetPosition": {
          "x": 2659.1162,
          "y": 301.94095,
          "z": 120.64831
        },
        "headTurnTime": 0.3,
        "targetNpcAlias": ""
      },
      {
        "$type": "MoleMole.Config.ConfigDialogInterAction",
        "type": "DIALOG",
        "aliasList": [
          "1005"
        ],
        "dialogID": 3930137,
        "protectTime": 0.6222823
      },
      {
        "$type": "MoleMole.Config.ConfigBodyLangInterAction",
        "type": "BODY_LANG",
        "aliasList": [
          "1005"
        ],
        "bodyLangParam": 1230
      },
      {
        "$type": "MoleMole.Config.ConfigEmoSyncInterAction",
        "type": "EMO_SYNC",
        "aliasList": [
          "1005"
        ],
        "dataPath": "Cs_Emo_Avatar_Simple_Common_Set/Cs_Emo_Avatar_Talk/Cs_Emo_Avatar_MainLine/Cs_Emo_Avatar_MengDe/Cs_Emo_3930137",
        "phonemePath": "",
        "emotionPath": "",
        "mateDataPath": "",
        "matePhonemePath": "",
        "mateEmotionPath": "",
        "dataPathHashList": [
          780558081153,
          180249455775,
          633791520495,
          618729972819
        ]
      }
    ],
    [
      {
        "$type": "MoleMole.Config.ConfigBlackScreenAction",
        "type": "BLACK_SCREEN",
        "duration": 0.8,
        "durationToBlack": 0.3,
        "durationKeepBlack": 0.2,
        "durationFromBlack": 0.3,
        "inteePos": "",
        "textMapID": ""
      },
      {
        "$type": "MoleMole.Config.ConfigCameraMoveInterAction",
        "type": "CAMERA_MOVE",
        "delayTime": 0.4,
        "camPosOffset": {
          "x": 2661.8418,
          "y": 302.78375,
          "z": 116.592224
        },
        "camForwardTargetOffset": {
          "x": 2661.3262,
          "y": 302.56107,
          "z": 117.419525
        },
        "lerpPattern": 6,
        "cameraBlendType": "EaseInOutCubic",
        "cutFrameTrans": {},
        "targetNpcAlias": ""
      },
      {
        "$type": "MoleMole.Config.ConfigDialogInterAction",
        "type": "DIALOG_CLEAR",
        "delayTime": 0.3,
        "protectTime": 0.19999999
      },
      {
        "$type": "MoleMole.Config.ConfigCameraDOFAction",
        "type": "CAMERA_DOF",
        "delayTime": 0.4,
        "focusDistance": 2.0,
        "focusRange": 3.0,
        "quality": 3
      },
      {
        "$type": "MoleMole.Config.ConfigTimeProtectAction",
        "type": "TIME_PROTECT",
        "duration": 0.8
      }
    ],
    [
      {
        "$type": "MoleMole.Config.ConfigLookAtInterAction",
        "type": "LOOK_AT",
        "aliasList": [
          "Avatar"
        ],
        "targetNpcAlias": ""
      },
      {
        "$type": "MoleMole.Config.ConfigLookAtInterAction",
        "type": "LOOK_AT",
        "aliasList": [
          "1001"
        ],
        "targetNpcAlias": ""
      },
      {
        "$type": "MoleMole.Config.ConfigLookAtInterAction",
        "type": "LOOK_AT",
        "aliasList": [
          "1009"
        ],
        "targetNpcAlias": ""
      },
      {
        "$type": "MoleMole.Config.ConfigLookAtInterAction",
        "type": "LOOK_AT",
        "aliasList": [
          "1006"
        ],
        "targetNpcAlias": ""
      },
      {
        "$type": "MoleMole.Config.ConfigLookAtInterAction",
        "type": "LOOK_AT",
        "aliasList": [
          "1005"
        ],
        "targetNpcAlias": ""
      }
    ]
  ],
  "groupId": [
    {
      "grpId": 3162378950,
      "nextGrpId": 3162378951
    },
    {
      "index": 1,
      "grpId": 3162378951,
      "nextGrpId": 3162378952
    },
    {
      "index": 2,
      "grpId": 3162378952,
      "nextGrpId": 3162378953
    },
    {
      "index": 3,
      "grpId": 3162378953,
      "nextGrpId": 3162378954
    },
    {
      "index": 4,
      "grpId": 3162378954,
      "nextGrpId": 3162378955
    },
    {
      "index": 5,
      "grpId": 3162378955,
      "nextGrpId": 3162378956
    },
    {
      "index": 6,
      "grpId": 3162378956,
      "nextGrpId": 3162378957
    },
    {
      "index": 7,
      "grpId": 3162378957,
      "nextGrpId": 3162378958
    },
    {
      "index": 8,
      "grpId": 3162378958,
      "nextGrpId": 3544466986
    },
    {
      "index": 9,
      "grpId": 3544466986,
      "nextGrpId": 3544466987
    },
    {
      "index": 10,
      "grpId": 3544466987,
      "nextGrpId": 3544466990
    },
    {
      "index": 11,
      "grpId": 3544466988,
      "nextGrpId": 3544466989
    },
    {
      "index": 12,
      "grpId": 3544466989,
      "nextGrpId": 3544466990
    },
    {
      "index": 13,
      "grpId": 3544466990,
      "nextGrpId": 3544466991
    },
    {
      "index": 14,
      "grpId": 3544466991,
      "nextGrpId": 3544466992
    },
    {
      "index": 15,
      "grpId": 3544466992,
      "nextGrpId": 3544466993
    },
    {
      "index": 16,
      "grpId": 3544466993,
      "nextGrpId": 3544466994
    },
    {
      "index": 17,
      "grpId": 3544466994,
      "nextGrpId": 3544466995
    },
    {
      "index": 18,
      "grpId": 3544466995,
      "nextGrpId": 3544467017
    },
    {
      "index": 19,
      "grpId": 3544467017,
      "nextGrpId": 3544467018
    },
    {
      "index": 20,
      "grpId": 3544467018,
      "nextGrpId": 3544467019
    },
    {
      "index": 21,
      "grpId": 3544467019,
      "nextGrpId": 3544467020
    },
    {
      "index": 22,
      "grpId": 3544467020,
      "nextGrpId": 3544467021
    },
    {
      "index": 23,
      "grpId": 3544467021,
      "nextGrpId": 3544467022
    },
    {
      "index": 24,
      "grpId": 3544467022,
      "nextGrpId": 3544467023
    },
    {
      "index": 25,
      "grpId": 3544467023,
      "nextGrpId": 3544467024
    },
    {
      "index": 26,
      "grpId": 3544467024,
      "nextGrpId": 3544467025
    },
    {
      "index": 27,
      "grpId": 3544467025,
      "nextGrpId": 3544467026
    },
    {
      "index": 28,
      "grpId": 3544467026,
      "nextGrpId": 3544467048
    }
  ],
  "freeStyleDic": {
    "1001": [
      1180,
      1170,
      1110,
      1130
    ],
    "1009": [
      1120
    ],
    "1006": [
      1130,
      1170
    ]
  }
}